Workbook

Sheet Net
A1: A. Sisa Aset PT BPR Legian (DL) - Netto
B3: Jenis Aset | C3: NP Audited | D3: Setoff Kredit | E3: LANAP | F3: Pencairan Aset s.d. Mei 2021 | G3: Nilai Aset Belum Diselesaikan | H3: % Pencairan (NP) | I3: % Pencairan (LANAP)
B4: (a) | C4: (b) | D4: (c) | E4: (d) | F4: (e) | G4: (f) = (b-c-e) | H4: (g) = (e/(b-c)) | I4: (h) = (e/d)
B5: Kas | C5: 41285600 | E5: 41285600 | F5: 41285600 | G5: =C5-D5-F5 -> 0 | H5: =F5/(C5-D5) -> 1 | I5: =F5/E5 -> 1
B6: Antar Bank Aktiva (ABA) | C6: 6.6624055e+09 | E6: =ABA!F19 -> 6.6624055e+09 | F6: =ABA!G19 -> 7.100292e+08 | G6: =ABA!H19 -> 6001320940 | H6: =F6/(C6-D6) -> 0.1065725 | I6: =F6/E6 -> 0.1065725
B7: Kredit | C7: 1.2695395e+11 | D7: =Kredit!N200 -> 4.2415871e+08 | E7: =Kredit!Z200 -> 1.0133058e+11 | F7: =Kredit!O200 -> 3.6047969e+10 | G7: =C7-D7-F7 -> 9.048182e+10 | H7: =F7/(C7-D7) -> 0.28489709 | I7: =F7/E7 -> 0.35574621
B8: PPAP | C8: -19448944940
B9: Kredit Net | C9: =SUM(C7:C8) -> 1.07505e+11
B10: Aktiva Tetap dan Inventaris | C10: 18360695711
B11: Ak. Penyusutan Aktiva Tetap dan Inventaris | C11: -5565273533
B12: Aktiva Tetap - Nilai Buku | C12: =SUM(C10:C11) -> 12795422178 | E12: ='Tanah dan Bangunan'!E4+Kendaraan!E16+Inventaris!E970 -> 1.4491562e+10 | F12: ='Tanah dan Bangunan'!F4+Kendaraan!F16+Inventaris!F970 -> 2674470000 | G12: ='Tanah dan Bangunan'!G4+Kendaraan!G16+Inventaris!G970 -> 13941214229 | H12: =F12/C12 -> 0.20901772 | I12: =F12/E12 -> 0.1845536
B13: Rupa-Rupa Aktiva
B14: - AYDA | C14: 2.0098758e+10 | E14: 1.3319078e+10 | F14: =AYDA!G25 -> 2.0585047e+09 | G14: =Net!C14-Net!F14 -> 1.8040253e+10 | H14: =F14/C14 -> 0.1024195 | I14: =F14/E14 -> 0.15455309
B15: - PYAD | C15: 239139829 | E15: 3910870709 | F15: =Kredit!P200 -> 3.9680295e+09 | G15: 0 | H15: =F15/C15 -> 16.592926 | I15: =F15/E15 -> 1.0146154
B16: - Akural Denda Kredit | C16: 0 | E16: 1998404527 | F16: =Kredit!Q200 -> 5.1152048e+08 | G16: 0
B17: - Penerimaan Lainnya | C17: 0 | E17: 571652278 | F17: 1.4492681e+09 | G17: 0
B18: Total RRA | C18: =SUM(C14:C17) -> 2.0337898e+10 | D18: =SUM(D14:D17) -> 0 | E18: =SUM(E14:E17) -> 1.9800006e+10 | F18: =SUM(F14:F17) -> 7.9873227e+09 | G18: =SUM(G14:G17) -> 1.8040253e+10 | H18: =F18/C18 -> 0.39273099 | I18: =F18/E18 -> 0.40340002
B19: Total Aset | C19: =C5+C6+C9+C12+C18 -> 1.4734201e+11 | D19: 0 | E19: =E5+E6+E7+E12+E18 -> 1.4232584e+11 | F19: =F5+F6+F7+F12+F18 -> 4.7461077e+10 | G19: =G5+G6+G7+G12+G18 -> 1.2846461e+11 | H19: =F19/C19 -> 0.32211503 | I19: =F19/E19 -> 0.33346775
C21: =SUM(C14:C17) -> 2.0337898e+10 | E21: =SUM(E14:E17) -> 1.9800006e+10 | F21: =SUM(F14:F17) -> 7.9873227e+09 | H21: =F21/C21 -> 0.39273099 | I21: =F21/E21 -> 0.40340002
E24: 97243104404
E25: =E7-E24 -> 4.0874746e+09

Sheet Gross
A1: A. Sisa Aset PT BPR Legian (DL) - Gross
B3: Jenis Aset | C3: NP Audited | D3: Setoff Kredit | E3: LANAP | F3: Pencairan Aset s.d. Mei 2021 | G3: Nilai Aset Belum Diselesaikan | H3: % Pencairan (NP) | I3: % Pencairan (LANAP)
B4: (a) | C4: (b) | D4: (c) | E4: (d) | F4: (e) | G4: (f) = (b-c-e) | H4: (g) = (e/(b-c)) | I4: (h) = (e/d)
B5: Kas | C5: 41285600 | E5: 41285600 | F5: 41285600 | G5: =C5-D5-F5 -> 0 | H5: =F5/(C5-D5) -> 1 | I5: =F5/E5 -> 1
B6: Antar Bank Aktiva (ABA) | C6: 6.6624055e+09 | E6: =ABA!F19 -> 6.6624055e+09 | F6: =ABA!G19 -> 7.100292e+08 | G6: =Net!G6 -> 6001320940 | H6: =F6/(C6-D6) -> 0.1065725 | I6: =F6/E6 -> 0.1065725
B7: Kredit | C7: 1.2695395e+11 | D7: =Kredit!N200 -> 4.2415871e+08 | E7: =Kredit!Z200 -> 1.0133058e+11 | F7: =Kredit!O200 -> 3.6047969e+10 | G7: =C7-D7-F7 -> 9.048182e+10 | H7: =F7/(C7-D7) -> 0.28489709 | I7: =F7/E7 -> 0.35574621
B8: Aktiva Tetap dan Inventaris | C8: 18360695711
B9: Ak. Penyusutan Aktiva Tetap dan Inventaris | C9: -5565273533
B10: Aktiva Tetap - Nilai Buku | C10: =SUM(C8:C9) -> 12795422178 | E10: ='Tanah dan Bangunan'!E4+Kendaraan!E16+Inventaris!E970 -> 1.4491562e+10 | F10: ='Tanah dan Bangunan'!F4+Kendaraan!F16+Inventaris!F970 -> 2674470000 | G10: =Net!G12 -> 13941214229 | H10: =F10/C10 -> 0.20901772 | I10: =F10/E10 -> 0.1845536
B11: Rupa-Rupa Aktiva
B12: - AYDA | C12: 2.0098758e+10 | E12: 1.3319078e+10 | F12: =AYDA!G25 -> 2.0585047e+09 | G12: =Net!G14 -> 1.8040253e+10 | H12: =F12/C12 -> 0.1024195 | I12: =F12/E12 -> 0.15455309
B13: - PYAD | C13: 239139829 | E13: 3910870709 | F13: =Kredit!P200 -> 3.9680295e+09 | G13: =Net!G15 -> 0 | H13: =F13/C13 -> 16.592926 | I13: =F13/E13 -> 1.0146154
B14: - Akural Denda Kredit | C14: 0 | E14: 1998404527 | F14: =Kredit!Q200 -> 5.1152048e+08 | G14: 0
B15: - Penerimaan Lainnya | C15: 0 | E15: 571652278 | F15: 1.4492681e+09 | G15: 0
B16: Total Aset | C16: =C5+C6+C7+C10+C12+C13+C14+C15 -> 1.6679096e+11 | D16: =D5+D6+D7+D10+D12+D13+D14+D15 -> 4.2415871e+08 | E16: =E5+E6+E7+E10+E12+E13+E14+E15 -> 1.4232584e+11 | F16: =F5+F6+F7+F10+F12+F13+F14+F15 -> 4.7461077e+10 | G16: =G5+G6+G7+G10+G12+G13+G14+G15 -> 1.2846461e+11 | H16: =F16/C16 -> 0.28455425 | I16: =F16/E16 -> 0.33346775

Sheet ABA
A2: No. | B2: Nomor Rekening | C2: Uraian Penempatan Pada Bank Lain | D2: Jenis Penempatan Dana | E2: Saldo (NP Audited) | F2: Saldo (LANAP) | G2: Realisasi Pencairan s.d. Mei 2021 | H2: Nilai Aset yang Belum Dicairkan | I2: Keterangan (Cair/Belum Dicairkan) | J2: Strategi Pencairan
A3: 1 | C3: Bank Mandiri - Cab Veteran Denpasar | D3: Giro dan Tabungan | E3: 1700828.8 | F3: 1700828.8 | G3: 1700828.8 | I3: Cair
A4: 2 | C4: Bank BNI Cab Renon Denpsr | D4: Giro dan Tabungan | E4: 76168683 | F4: 76168683 | G4: 76168683 | I4: Cair
A5: 3 | C5: Bank BPD Bali Cab Renon Dpsr | D5: Giro dan Tabungan | E5: 1083390.9 | F5: 1083390.9 | G5: 1083390.9 | I5: Cair
A6: 4 | C6: Bank BCA | D6: Giro dan Tabungan | E6: 10874624 | F6: 10874624 | G6: 10874624 | I6: Cair
A7: 5 | C7: Bank CIMB Niaga | D7: Giro dan Tabungan | E7: 376954845 | F7: 376954845 | G7: 3.7798736e+08 | I7: Cair
A8: 6 | C8: Bank Permata - Dewi Sartika | D8: Giro dan Tabungan | E8: 5001320940 | F8: 5001320940 | G8: 0 | H8: =E8 -> 5001320940 | I8: Belum Cair | J8: Setoff dengan Kewajiban BDL
A9: 7 | C9: Bank Danamon | D9: Giro dan Tabungan | E9: 1973136 | F9: 1973136 | G9: 1973136 | I9: Cair
A10: 8 | C10: Bank BCA | D10: Giro dan Tabungan | E10: 1541708.4 | F10: 1541708.4 | G10: 1541708.4 | I10: Cair
A11: 9 | C11: Bank OK Bank Indonesia | D11: Giro dan Tabungan | E11: 47333657 | F11: 47333657 | G11: 52617188 | I11: Cair
A12: 10 | C12: Bank BNI Cab Renon Denpsr | D12: Giro dan Tabungan | E12: 1343862 | F12: 1343862 | G12: 1343862 | I12: Cair
A13: 11 | C13: Bank Andara - Denpasar | D13: Giro dan Tabungan | E13: 819490.43 | F13: 819490.43 | G13: 819490 | I13: Cair
A14: 12 | C14: Bank BPR Lestari - Denpasar | D14: Giro dan Tabungan | E14: 1461133 | F14: 1461133 | G14: 1461133 | I14: Cair
A15: 13 | C15: Bank BPR Supra - Sukabumi | D15: Giro dan Tabungan | E15: 39829158 | F15: 39829158 | G15: 39829158 | I15: Cair
A16: 14 | C16: Bank Andara - Denpasar | D16: Deposito | E16: 100000000 | F16: 100000000 | G16: 100000000 | I16: Cair
A17: 15 | C17: Bank OK Bank Indonesia | D17: Deposito | E17: 500000000 | F17: 500000000 | G17: 35759621 | H17: =E17 -> 500000000 | I17: Belum Cair | J17: Setoff dengan Kewajiban BDL
A18: 16 | C18: Bank BPR Supra - Sukabumi | D18: Deposito | E18: 500000000 | F18: 500000000 | G18: 6869011.6 | H18: =E18 -> 500000000 | I18: Belum Cair | J18: Setoff dengan Kewajiban BDL
E19: =SUM(E3:E18) -> 6.6624055e+09 | F19: =SUM(F3:F18) -> 6.6624055e+09 | G19: =SUM(G3:G18) -> 7.100292e+08 | H19: =SUM(H3:H18) -> 6001320940
B57: Total | D57: =SUM(D3:D56) -> 0

Sheet Kredit
K2: data set off GPKL
A3: No. | B3: Nomor Rekening | C3: Nama Debitur | D3: Kol. | E3: Baki Debet (NP Audited) | F3: Bunga (NP Audited) | G3: Denda (NP Audited) | H3: Total Kewajiban (NP Audited) | I3: Penyesuaian Bunga Berjalan | J3: Penyesuaian Denda Berjalan | K3: Setoff Pokok | L3: Setoff Bunga | M3: Setoff Denda | N3: Total Setoff | O3: Pencairan Pokok s.d Mei 2021 | P3: Pencairan Bunga s.d Mei 2021 | Q3: Pencairan Denda s.d Mei 2021 | R3: Total Pencairan s.d Mei 2021 | S3: Haircut Bunga s.d Mei 2021 | T3: Haircut Denda s.d Mei 2021 | U3: Sisa Kewajiban Pokok Mei 2021 | V3: Sisa Kewajiban Bunga s.d. Mei 2021 | W3: Sisa Kewajiban Denda s.d. Mei 2021 | X3: Total Sisa Kewajiban s.d. Mei 2021 | Y3: Nilai Likuidasi | Z3: LANAP | AA3: Jenis Agunan | AB3: Jenis Pengikatan | AC3: Keterangan | AD3: Strategi Pencairan | AE3: 44348 | AF3: 44378 | AG3: 44409 | AH3: 44440 | AI3: 44470 | AJ3: 44501 | AK3: 44531 | AL3: 44562 | AM3: 44593 | AN3: 44621 | AO3: 44652 | AP3: 44682 | AQ3: 44713 | AR3: Total
A4: 1 | B4: 02.300408 | C4: Bunardi Podjan | D4: 1 | E4: 7.6251493e+08 | F4: 11231783 | G4: 10972502 | H4: =SUM(E4:G4) -> 7.8471922e+08 | I4: 0 | J4: 0 | K4: 0 | N4: =SUM(K4:M4) -> 0 | O4: 396000000 | P4: 0 | Q4: 0 | R4: =SUM(O4:Q4) -> 396000000 | S4: 0 | T4: 0 | U4: =E4-K4-O4 -> 3.6651493e+08 | V4: =F4+I4-P4-S4 -> 11231783 | W4: =G4+J4-M4-Q4-T4 -> 10972502 | X4: =SUM(U4:W4) -> 3.8871922e+08 | Y4: 1131000000 | Z4: 762514931 | AA4: SHM | AB4: SHT | AC4: Belum Lunas | AD4: Take Over | AE4: 17052632 | AF4: 17052632 | AG4: 17052632 | AH4: 17052632 | AI4: 17052632 | AJ4: 17052632 | AK4: 17052632 | AL4: 17052632 | AM4: 17052632 | AN4: 17052632 | AO4: 17052632 | AP4: =U4-(SUM(AE4:AO4)) -> 1.7893598e+08 | AQ4: 0 | AR4: =SUM(AE4:AQ4) -> 3.6651493e+08
A5: 2 | B5: 02.300506 | C5: Wilman Ardan | D5: 1 | E5: 75054324 | F5: 598573 | G5: 2966605.1 | H5: =SUM(E5:G5) -> 78619502 | I5: 28545351 | J5: 0 | K5: 9023 | N5: =SUM(K5:M5) -> 9023 | O5: 75045301 | P5: 29143924 | Q5: 2966605.1 | R5: =SUM(O5:Q5) -> 1.0715583e+08 | S5: 0 | T5: 0 | U5: =E5-K5-O5 -> 0 | V5: =F5+I5-P5-S5 -> 0 | W5: =G5+J5-M5-Q5-T5 -> 0 | X5: =SUM(U5:W5) -> 0 | Y5: 131000000 | Z5: 75045301 | AA5: SHM | AB5: SHT | AC5: Lunas | AD5: Take Over | AQ5: 0 | AR5: =SUM(AE5:AQ5) -> 0
A6: 3 | B6: 02.300100 | C6: Luluk Badria Murni | D6: 1 | E6: 57660605 | F6: 1365896 | G6: 10489875 | H6: =SUM(E6:G6) -> 69516376 | I6: 11705101 | J6: 10215385 | K6: 8051 | N6: =SUM(K6:M6) -> 8051 | O6: =57660605.07-8051 -> 57652554 | P6: 13070997 | Q6: 20705260 | R6: =SUM(O6:Q6) -> 91428811 | S6: 0 | T6: 0 | U6: =E6-K6-O6 -> 0 | V6: =F6+I6-P6-S6 -> 0 | W6: =G6+J6-M6-Q6-T6 -> 0 | X6: =SUM(U6:W6) -> 0 | Y6: 0 | Z6: 57652554 | AA6: SHM | AB6: SHT | AC6: Lunas | AD6: Lelang KPKNL | AQ6: 0 | AR6: =SUM(AE6:AQ6) -> 0
A7: 4 | B7: 02.300353 | C7: Rokhim | D7: 1 | E7: 47930622 | F7: 263618 | G7: 0 | H7: =SUM(E7:G7) -> 48194240 | I7: 95862 | J7: 2412898 | K7: 0 | N7: =SUM(K7:M7) -> 0 | O7: 47930622 | P7: 359480 | Q7: 2412898 | R7: =SUM(O7:Q7) -> 50703000 | S7: 0 | T7: 0 | U7: =E7-K7-O7 -> 0 | V7: =F7+I7-P7-S7 -> 0 | W7: =G7+J7-M7-Q7-T7 -> 0 | X7: =SUM(U7:W7) -> 0 | Y7: 0 | Z7: 47930622 | AA7: SHM | AB7: SHT | AC7: Lunas | AD7: Lelang KPKNL | AQ7: 0 | AR7: =SUM(AE7:AQ7) -> 0
A8: 5 | B8: 02.300531 | C8: Raju Lusmana | D8: 1 | E8: 6.6148787e+08 | F8: 12237526 | G8: 82574662 | H8: =SUM(E8:G8) -> 7.5630006e+08 | I8: 12035228 | J8: 1146508 | K8: 0 | N8: =SUM(K8:M8) -> 0 | O8: 6.6148787e+08 | P8: 24272754 | Q8: 83721170 | R8: =SUM(O8:Q8) -> 7.6948179e+08 | S8: 0 | T8: 0 | U8: =E8-K8-O8 -> 0 | V8: =F8+I8-P8-S8 -> 0 | W8: =G8+J8-M8-Q8-T8 -> 0 | X8: =SUM(U8:W8) -> 0 | Y8: 0 | Z8: 661487869 | AA8: SHM | AB8: SHT | AC8: Lunas | AD8: Lelang KPKNL | AQ8: 0 | AR8: =SUM(AE8:AQ8) -> 0
A9: 6 | B9: 02.300539 | C9: Kadek Ngurah Robi Juniawan | D9: 1 | E9: 1.6471044e+08 | F9: 1422000 | G9: 0 | H9: =SUM(E9:G9) -> 1.6613244e+08 | I9: 6483419 | J9: 6000 | K9: 20738744 | N9: =SUM(K9:M9) -> 20738744 | O9: 1.439717e+08 | P9: 7905419 | Q9: 6000 | R9: =SUM(O9:Q9) -> 1.5188311e+08 | S9: 0 | T9: 0 | U9: =E9-K9-O9 -> 0 | V9: =F9+I9-P9-S9 -> 0 | W9: =G9+J9-M9-Q9-T9 -> 0 | X9: =SUM(U9:W9) -> 0 | Y9: 0 | Z9: 143971695 | AA9: SHM | AB9: SHT | AC9: Lunas | AD9: Lelang KPKNL | AQ9: 0 | AR9: =SUM(AE9:AQ9) -> 0
A10: 7 | B10: 02.300602 | C10: Putu Ayu Junita Sari | D10: 1 | E10: 38800844 | F10: 206937.72 | G10: 0 | H10: =SUM(E10:G10) -> 39007782 | I10: 0 | J10: 0 | K10: 0 | N10: =SUM(K10:M10) -> 0 | O10: 24527180 | P10: 0 | Q10: 0 | R10: =SUM(O10:Q10) -> 24527180 | S10: 0 | T10: 0 | U10: =E10-K10-O10 -> 14273664 | V10: =F10+I10-P10-S10 -> 206937.72 | W10: =G10+J10-M10-Q10-T10 -> 0 | X10: =SUM(U10:W10) -> 14480602 | Y10: 477000000 | Z10: 38800844 | AA10: SHM | AB10: SHT | AC10: Belum Lunas | AD10: Penagihan Langsung | AE10: 1044302 | AF10: 1044302 | AG10: 1044302 | AH10: 1044302 | AI10: 1044302 | AJ10: 1044302 | AK10: 1044302 | AL10: 1044302 | AM10: 1044302 | AN10: 1044302 | AO10: 1044302 | AP10: =U10-(SUM(AE10:AO10)) -> 2786342.5 | AQ10: 0 | AR10: =SUM(AE10:AQ10) -> 14273664
A11: 8 | B11: 02.300625 | C11: Made Ita Yulita | D11: 1 | E11: 35148500 | F11: 171837 | G11: 0 | H11: =SUM(E11:G11) -> 35320337 | I11: 5686809 | J11: 0 | K11: 84346 | N11: =SUM(K11:M11) -> 84346 | O11: =35061583.76+2570 -> 35064154 | P11: 5858646 | Q11: 0 | R11: =SUM(O11:Q11) -> 40922800 | S11: 0 | T11: 0 | U11: =E11-K11-O11 -> 0 | V11: =F11+I11-P11-S11 -> 0 | W11: =G11+J11-M11-Q11-T11 -> 0 | X11: =SUM(U11:W11) -> 0 | Y11: 0 | Z11: 13014860 | AA11: SHM | AB11: Tidak Ada Pengikatan | AC11: Lunas | AD11: Penagihan Langsung | AQ11: 0 | AR11: =SUM(AE11:AQ11) -> 0
A12: 9 | B12: 02.300666 | C12: Putu Ayu Junita Sari | D12: 1 | E12: 25560631 | F12: 11360.28 | G12: 0 | H12: =SUM(E12:G12) -> 25571991 | I12: 0 | J12: 0 | K12: 0.35219068 | N12: =SUM(K12:M12) -> 0.35219068 | O12: 12442231 | P12: 0 | Q12: 0 | R12: =SUM(O12:Q12) -> 12442231 | S12: 0 | T12: 0 | U12: =E12-K12-O12 -> 13118399 | V12: =F12+I12-P12-S12 -> 11360.28 | W12: =G12+J12-M12-Q12-T12 -> 0 | X12: =SUM(U12:W12) -> 13129760 | Y12: 0 | Z12: 6589591.6 | AA12: SHM | AB12: SHT | AC12: Belum Lunas | AD12: Penagihan Langsung | AE12: 517853.21 | AF12: 517853.21 | AG12: 517853.21 | AH12: 517853.21 | AI12: 517853.21 | AJ12: 517853.21 | AK12: 517853.21 | AL12: 517853.21 | AM12: 517853.21 | AN12: 517853.21 | AO12: 517853.21 | AP12: =U12-(SUM(AE12:AO12)) -> 7422014 | AQ12: 0 | AR12: =SUM(AE12:AQ12) -> 13118399
A13: 10 | B13: 02.300681 | C13: I Nyoman Sidia | D13: 1 | E13: 7.4125969e+08 | F13: 6486022.2 | G13: 221818.86 | H13: =SUM(E13:G13) -> 7.4796753e+08 | I13: 0 | J13: 0 | K13: 9023 | N13: =SUM(K13:M13) -> 9023 | O13: 139109592 | P13: 0 | Q13: 0 | R13: =SUM(O13:Q13) -> 139109592 | S13: 0 | T13: 0 | U13: =E13-K13-O13 -> 6.0214107e+08 | V13: =F13+I13-P13-S13 -> 6486022.2 | W13: =G13+J13-M13-Q13-T13 -> 221818.86 | X13: =SUM(U13:W13) -> 6.0884892e+08 | Y13: 1220000000 | Z13: 741250667 | AA13: SHM | AB13: SHT | AC13: Belum Lunas | AD13: Lelang KPKNL | AF13: 6.0884892e+08 | AQ13: 0 | AR13: =SUM(AE13:AQ13) -> 6.0884892e+08
A14: 11 | B14: 02.300695 | C14: Made Wira Sastrawan | D14: 1 | E14: 3970117.9 | F14: 31761 | G14: 0 | H14: =SUM(E14:G14) -> 4001878.9 | I14: 404796 | J14: 0 | K14: 35351 | N14: =SUM(K14:M14) -> 35351 | O14: 3934766.9 | P14: 436557 | Q14: 0 | R14: =SUM(O14:Q14) -> 4371323.9 | S14: 0 | T14: 0 | U14: =E14-K14-O14 -> 0 | V14: =F14+I14-P14-S14 -> 0 | W14: =G14+J14-M14-Q14-T14 -> 0 | X14: =SUM(U14:W14) -> 0 | Y14: 0 | Z14: 1175116 | AA14: BPKB | AB14: Tidak Ada Pengikatan | AC14: Lunas | AD14: Penagihan Langsung | AQ14: 0 | AR14: =SUM(AE14:AQ14) -> 0
A15: 12 | B15: 02.300701 | C15: I Ketut Sariyana | D15: 1 | E15: 8170422.4 | F15: 72626 | G15: 0 | H15: =SUM(E15:G15) -> 8243048.4 | I15: 1439405 | J15: 0 | K15: 30699 | N15: =SUM(K15:M15) -> 30699 | O15: 8139723.4 | P15: 1512031 | Q15: 0 | R15: =SUM(O15:Q15) -> 9651754.4 | S15: 0 | T15: 0 | U15: =E15-K15-O15 -> 0 | V15: =F15+I15-P15-S15 -> 0 | W15: =G15+J15-M15-Q15-T15 -> 0 | X15: =SUM(U15:W15) -> 0 | Y15: 0 | Z15: 5273550 | AA15: BPKB | AB15: Tidak Ada Pengikatan | AC15: Lunas | AD15: Penagihan Langsung | AQ15: 0 | AR15: =SUM(AE15:AQ15) -> 0
A16: 13 | B16: 02.300702 | C16: I Gede Dananjaya Siadja | D16: 1 | E16: 5.6666523e+08 | F16: 8074979 | G16: 0 | H16: =SUM(E16:G16) -> 5.7474021e+08 | I16: 41922585 | J16: 64294 | K16: 34315042 | N16: =SUM(K16:M16) -> 34315042 | O16: 5.3235019e+08 | P16: 49997564 | Q16: 64294 | R16: =SUM(O16:Q16) -> 5.8241204e+08 | S16: 0 | T16: 0 | U16: =E16-K16-O16 -> 0 | V16: =F16+I16-P16-S16 -> 0 | W16: =G16+J16-M16-Q16-T16 -> 0 | X16: =SUM(U16:W16) -> 0 | Y16: 0 | Z16: 532350186 | AA16: SHM | AB16: SHT | AC16: Lunas | AD16: Lelang KPKNL | AQ16: 0 | AR16: =SUM(AE16:AQ16) -> 0
A17: 14 | B17: 02.300703 | C17: Ni Nengah Nuasih | D17: 1 | E17: 16340836 | F17: 137989 | G17: 0 | H17: =SUM(E17:G17) -> 16478825 | I17: 2772161 | J17: 0 | K17: 56496 | N17: =SUM(K17:M17) -> 56496 | O17: 16284340 | P17: 2910150 | Q17: 0 | R17: =SUM(O17:Q17) -> 19194490 | S17: 0 | T17: 0 | U17: =E17-K17-O17 -> 0 | V17: =F17+I17-P17-S17 -> 0 | W17: =G17+J17-M17-Q17-T17 -> 0 | X17: =SUM(U17:W17) -> 0 | Y17: 0 | Z17: 7670128 | AA17: BPKB | AB17: Tidak Ada Pengikatan | AC17: Lunas | AD17: Penagihan Langsung | AQ17: 0 | AR17: =SUM(AE17:AQ17) -> 0
A18: 15 | B18: 02.300707 | C18: I Ketut Subagia | D18: 1 | E18: 72632800 | F18: 355093.64 | G18: 0 | H18: =SUM(E18:G18) -> 72987894 | I18: 17661768 | J18: 0 | K18: 48103 | N18: =SUM(K18:M18) -> 48103 | O18: =72632800-48103 -> 72584697 | P18: 18016862 | Q18: 0 | R18: =SUM(O18:Q18) -> 90601559 | S18: 0 | T18: 0 | U18: 0 | V18: =F18+I18-P18-S18 -> 0 | W18: =G18+J18-M18-Q18-T18 -> 0 | X18: =SUM(U18:W18) -> 0 | Y18: 0 | Z18: 29181685 | AA18: SHM | AB18: Tidak Ada Pengikatan | AC18: Lunas | AD18: Penagihan Langsung | AQ18: 0 | AR18: =SUM(AE18:AQ18) -> 0
A19: 16 | B19: 02.300709 | C19: I Putu Widi Indriyana | D19: 1 | E19: 29434506 | F19: 353214 | G19: 0 | H19: =SUM(E19:G19) -> 29787720 | I19: 4399453 | J19: 0 | K19: 95713 | N19: =SUM(K19:M19) -> 95713 | O19: =29434506-95713 -> 29338793 | P19: 4752667 | Q19: 0 | R19: =SUM(O19:Q19) -> 34091460 | S19: 0 | T19: 0 | U19: 0 | V19: =F19+I19-P19-S19 -> 0 | W19: =G19+J19-M19-Q19-T19 -> 0 | X19: =SUM(U19:W19) -> 0 | Y19: 0 | Z19: 29338793 | AA19: BPKB | AB19: Tidak Ada Pengikatan | AC19: Lunas | AD19: Penagihan Langsung | AQ19: 0 | AR19: =SUM(AE19:AQ19) -> 0
A20: 17 | B20: 02.300714 | C20: I Wayan Widiatmika Kurniawan | D20: 1 | E20: 11105856 | F20: 64167 | G20: 0 | H20: =SUM(E20:G20) -> 11170023 | I20: 767759 | J20: 0 | K20: 127596 | N20: =SUM(K20:M20) -> 127596 | O20: =11105856-127596 -> 10978260 | P20: 831926 | Q20: 0 | R20: =SUM(O20:Q20) -> 11810186 | S20: 0 | T20: 0 | U20: 0 | V20: =F20+I20-P20-S20 -> 0 | W20: =G20+J20-M20-Q20-T20 -> 0 | X20: =SUM(U20:W20) -> 0 | Y20: 0 | Z20: 10978260 | AA20: BPKB | AB20: Tidak Ada Pengikatan | AC20: Lunas | AD20: Penagihan Langsung | AQ20: 0 | AR20: =SUM(AE20:AQ20) -> 0
A21: 18 | B21: 02.300721 | C21: I Putu Gede Wirawan | D21: 1 | E21: 12463477 | F21: 149562 | G21: 0 | H21: =SUM(E21:G21) -> 12613039 | I21: 1637896 | J21: 0 | K21: 63434 | N21: =SUM(K21:M21) -> 63434 | O21: 12400043 | P21: 1787458 | Q21: 0 | R21: =SUM(O21:Q21) -> 14187501 | S21: 0 | T21: 0 | U21: =E21-K21-O21 -> 0 | V21: =F21+I21-P21-S21 -> 0 | W21: =G21+J21-M21-Q21-T21 -> 0 | X21: =SUM(U21:W21) -> 0 | Y21: 0 | Z21: 8917510 | AA21: BPKB | AB21: Tidak Ada Pengikatan | AC21: Lunas | AD21: Penagihan Langsung | AQ21: 0 | AR21: =SUM(AE21:AQ21) -> 0
A22: 19 | B22: 02.300737 | C22: I Putu Wastika | D22: 1 | E22: 45345152 | F22: 80613.6 | G22: 0 | H22: =SUM(E22:G22) -> 45425765 | I22: 0 | J22: 0 | K22: 63773 | N22: =SUM(K22:M22) -> 63773 | O22: 12172098 | P22: 0 | Q22: 0 | R22: =SUM(O22:Q22) -> 12172098 | S22: 0 | T22: 0 | U22: =E22-K22-O22 -> 33109281 | V22: =F22+I22-P22-S22 -> 80613.6 | W22: =G22+J22-M22-Q22-T22 -> 0 | X22: =SUM(U22:W22) -> 33189894 | Y22: 0 | Z22: 2253000 | AA22: BPKB | AB22: Tidak Ada Pengikatan | AC22: Belum Lunas | AD22: Cessie | AQ22: 1655464 | AR22: =SUM(AE22:AQ22) -> 1655464 | AT22: =AR22/U22 -> 0.05
A23: 20 | B23: 02.200010 | C23: Supyan Yusuf | D23: 1 | E23: 25300984 | F23: 215901 | G23: 2417073 | H23: =SUM(E23:G23) -> 27933958 | I23: 312978 | J23: 47064 | K23: 0 | N23: =SUM(K23:M23) -> 0 | O23: 25300984 | P23: 528879 | Q23: 2464137 | R23: =SUM(O23:Q23) -> 28294000 | S23: 0 | T23: 0 | U23: =E23-K23-O23 -> 0 | V23: =F23+I23-P23-S23 -> 0 | W23: =G23+J23-M23-Q23-T23 -> 0 | X23: =SUM(U23:W23) -> 0 | Y23: 0 | Z23: 25300984 | AA23: SHM | AB23: SHT | AC23: Lunas | AD23: Lelang KPKNL | AQ23: 0 | AR23: =SUM(AE23:AQ23) -> 0
A24: 21 | B24: 02.200125 | C24: Darmika Dewa Gede | D24: 1 | E24: 50005033 | F24: 373371 | G24: 305152 | H24: =SUM(E24:G24) -> 50683556 | I24: 709327 | J24: 6000 | K24: 0 | N24: =SUM(K24:M24) -> 0 | O24: 50005033 | P24: 1082698 | Q24: 311152 | R24: =SUM(O24:Q24) -> 51398883 | S24: 0 | T24: 0 | U24: =E24-K24-O24 -> 0 | V24: =F24+I24-P24-S24 -> 0 | W24: =G24+J24-M24-Q24-T24 -> 0 | X24: =SUM(U24:W24) -> 0 | Y24: 0 | Z24: 50005033 | AA24: SHM | AB24: SHT | AC24: Lunas | AD24: Lelang KPKNL | AQ24: 0 | AR24: =SUM(AE24:AQ24) -> 0
A25: 22 | B25: 02.200335 | C25: Aloisius Rendi Holo | D25: 1 | E25: 23599551 | F25: 73421 | G25: 0 | H25: =SUM(E25:G25) -> 23672972 | I25: 1691586 | J25: 0 | K25: 0 | N25: =SUM(K25:M25) -> 0 | O25: 23599551 | P25: 1765007 | Q25: 0 | R25: =SUM(O25:Q25) -> 25364558 | S25: 0 | T25: 0 | U25: =E25-K25-O25 -> 0 | V25: =F25+I25-P25-S25 -> 0 | W25: =G25+J25-M25-Q25-T25 -> 0 | X25: =SUM(U25:W25) -> 0 | Y25: 0 | Z25: 23599551 | AA25: BPKB | AB25: Tidak Ada Pengikatan | AC25: Lunas | AD25: Penagihan Langsung | AQ25: 0 | AR25: =SUM(AE25:AQ25) -> 0
A26: 23 | B26: 02.200337 | C26: Anak Agung Istri Vera Raditya | D26: 1 | E26: 65803638 | F26: 175476 | G26: 0 | H26: =SUM(E26:G26) -> 65979114 | I26: 2292415 | J26: 0 | K26: 0 | N26: =SUM(K26:M26) -> 0 | O26: 65803638 | P26: 2467891 | Q26: 0 | R26: =SUM(O26:Q26) -> 68271529 | S26: 0 | T26: 0 | U26: =E26-K26-O26 -> 0 | V26: =F26+I26-P26-S26 -> 0 | W26: =G26+J26-M26-Q26-T26 -> 0 | X26: =SUM(U26:W26) -> 0 | Y26: 0 | Z26: 65803638 | AA26: BPKB | AB26: Tidak Ada Pengikatan | AC26: Lunas | AD26: Penagihan Langsung | AQ26: 0 | AR26: =SUM(AE26:AQ26) -> 0
A27: 24 | B27: 02.200342 | C27: Aloisius Rendi Holo | D27: 1 | E27: 483191.4 | F27: 0 | G27: 0 | H27: =SUM(E27:G27) -> 483191.4 | I27: 6440 | J27: 0 | K27: 0 | N27: =SUM(K27:M27) -> 0 | O27: 483191.4 | P27: 6440 | Q27: 0 | R27: =SUM(O27:Q27) -> 489631.4 | S27: 0 | T27: 0 | U27: =E27-K27-O27 -> 0 | V27: =F27+I27-P27-S27 -> 0 | W27: =G27+J27-M27-Q27-T27 -> 0 | X27: =SUM(U27:W27) -> 0 | Y27: 0 | Z27: 483191 | AA27: BPKB | AB27: Tidak Ada Pengikatan | AC27: Lunas | AD27: Penagihan Langsung | AQ27: 0 | AR27: =SUM(AE27:AQ27) -> 0
A28: 25 | B28: 02.200357 | C28: Dewa Nyoman Widnyana | D28: 1 | E28: 3.9573665e+08 | F28: 1846771 | G28: 0 | H28: =SUM(E28:G28) -> 3.9758342e+08 | I28: 0 | J28: 0 | K28: 120862 | N28: =SUM(K28:M28) -> 120862 | O28: 147500000 | P28: 0 | Q28: 0 | R28: =SUM(O28:Q28) -> 147500000 | S28: 0 | T28: 0 | U28: =E28-K28-O28 -> 2.4811579e+08 | V28: =F28+I28-P28-S28 -> 1846771 | W28: =G28+J28-M28-Q28-T28 -> 0 | X28: =SUM(U28:W28) -> 2.4996256e+08 | Y28: 351000000 | Z28: 358000000 | AA28: SHM | AB28: SHT | AC28: Belum Lunas | AD28: Lelang KPKNL | AG28: 2.4996256e+08 | AQ28: 0 | AR28: =SUM(AE28:AQ28) -> 2.4996256e+08
A29: 26 | B29: 02.100361 | C29: I Wayan Mertawa SH | D29: 1 | E29: 12553932 | F29: 224506 | G29: 1259140 | H29: =SUM(E29:G29) -> 14037578 | I29: 257995 | J29: 98627 | K29: 0 | N29: =SUM(K29:M29) -> 0 | O29: 12553932 | P29: 482501 | Q29: 1357767 | R29: =SUM(O29:Q29) -> 14394200 | S29: 0 | T29: 0 | U29: =E29-K29-O29 -> 0 | V29: =F29+I29-P29-S29 -> 0 | W29: =G29+J29-M29-Q29-T29 -> 0 | X29: =SUM(U29:W29) -> 0 | Y29: 0 | Z29: 12553932 | AA29: SHM | AB29: SKMHT | AC29: Lunas | AD29: Penagihan Langsung | AQ29: 0 | AR29: =SUM(AE29:AQ29) -> 0
A30: 27 | B30: 02.100377 | C30: Ni Pande Putu Andri Liani | D30: 1 | E30: 10505589 | F30: 297003 | G30: 166802 | H30: =SUM(E30:G30) -> 10969394 | I30: 19553 | J30: 349053 | K30: 0 | N30: =SUM(K30:M30) -> 0 | O30: 10505589 | P30: 316556 | Q30: 515855 | R30: =SUM(O30:Q30) -> 11338000 | S30: 0 | T30: 0 | U30: =E30-K30-O30 -> 0 | V30: =F30+I30-P30-S30 -> 0 | W30: =G30+J30-M30-Q30-T30 -> 0 | X30: =SUM(U30:W30) -> 0 | Y30: 0 | Z30: 10505589 | AA30: SHM | AB30: SHT | AC30: Lunas | AD30: Lelang KPKNL | AQ30: 0 | AR30: =SUM(AE30:AQ30) -> 0
A31: 28 | B31: 02.100382 | C31: Made Ayu Ima Pradasari | D31: 1 | E31: 13716015 | F31: 276507 | G31: 21808954 | H31: =SUM(E31:G31) -> 35801476 | I31: 234085 | J31: 0 | K31: 0 | N31: =SUM(K31:M31) -> 0 | O31: 13716015 | P31: 510592 | Q31: 53392 | R31: =SUM(O31:Q31) -> 14279999 | S31: 0 | T31: 21755562 | U31: =E31-K31-O31 -> 0 | V31: =F31+I31-P31-S31 -> 0 | W31: =G31+J31-M31-Q31-T31 -> 0 | X31: =SUM(U31:W31) -> 0 | Y31: 0 | Z31: 13716015 | AA31: SHM | AB31: SHT | AC31: Lunas | AD31: Lelang KPKNL | AQ31: 0 | AR31: =SUM(AE31:AQ31) -> 0
A32: 29 | B32: 02.100437 | C32: Ni Made Ayu Sita Setyawati | D32: 1 | E32: 92500000 | F32: 388500 | G32: 0 | H32: =SUM(E32:G32) -> 92888500 | I32: 777000 | J32: 2791000 | K32: 0 | N32: =SUM(K32:M32) -> 0 | O32: 92500000 | P32: 1165500 | Q32: 2791000 | R32: =SUM(O32:Q32) -> 96456500 | S32: 0 | T32: 0 | U32: =E32-K32-O32 -> 0 | V32: =F32+I32-P32-S32 -> 0 | W32: =G32+J32-M32-Q32-T32 -> 0 | X32: =SUM(U32:W32) -> 0 | Y32: 0 | Z32: 92500000 | AA32: SHM | AB32: SHT | AC32: Lunas | AD32: Lelang KPKNL | AQ32: 0 | AR32: =SUM(AE32:AQ32) -> 0
A33: 30 | B33: 02.100449 | C33: Ni Wayan Astini | D33: 1 | E33: 47516925 | F33: 211186 | G33: 0 | H33: =SUM(E33:G33) -> 47728111 | I33: 546971 | J33: 0 | K33: 0 | N33: =SUM(K33:M33) -> 0 | O33: 47516925 | P33: 758157 | Q33: 0 | R33: =SUM(O33:Q33) -> 48275082 | S33: 0 | T33: 0 | U33: =E33-K33-O33 -> 0 | V33: =F33+I33-P33-S33 -> 0 | W33: =G33+J33-M33-Q33-T33 -> 0 | X33: =SUM(U33:W33) -> 0 | Y33: 0 | Z33: 47516925 | AA33: BPKB | AB33: Tidak Ada Pengikatan | AC33: Lunas | AD33: Penagihan Langsung | AQ33: 0 | AR33: =SUM(AE33:AQ33) -> 0
A34: 31 | B34: 02.100404 | C34: I Gede Ketut Dinamika | D34: 1 | E34: 24875216 | F34: 1767712 | G34: 6690777 | H34: =SUM(E34:G34) -> 33333705 | I34: 340902 | J34: 277480 | K34: 0 | N34: =SUM(K34:M34) -> 0 | O34: 24875216 | P34: 2108614 | Q34: 6968257 | R34: =SUM(O34:Q34) -> 33952087 | S34: 0 | T34: 0 | U34: 0 | V34: =F34+I34-P34-S34 -> 0 | W34: =G34+J34-M34-Q34-T34 -> 0 | X34: =SUM(U34:W34) -> 0 | Y34: 0 | Z34: 24875217 | AA34: SHM | AB34: SKMHT | AC34: Lunas | AD34: Penagihan Langsung | AQ34: 0 | AR34: =SUM(AE34:AQ34) -> 0
A35: 32 | B35: 02.300667 | C35: I Ketut Minsana | D35: 1 | E35: 109374995 | F35: 2233593 | G35: 0 | H35: =SUM(E35:G35) -> 111608588 | I35: 5414062 | J35: 167000 | K35: 0 | N35: =SUM(K35:M35) -> 0 | O35: 109374995 | P35: 7647655 | Q35: 167000 | R35: =SUM(O35:Q35) -> 117189650 | S35: 0 | T35: 0 | U35: =E35-K35-O35 -> 0 | V35: =F35+I35-P35-S35 -> 0 | W35: =G35+J35-M35-Q35-T35 -> 0 | X35: =SUM(U35:W35) -> 0 | Y35: 0 | Z35: 1.0946986e+08 | AA35: SHM | AB35: SHT | AC35: Lunas | AD35: Lelang KPKNL | AQ35: 0 | AR35: =SUM(AE35:AQ35) -> 0
A36: 33 | B36: 02.300561 | C36: Pt.Bali Selancar Laut Biru | D36: 1 | E36: 3.967943e+08 | F36: 3915037 | G36: 434633 | H36: =SUM(E36:G36) -> 4.0114397e+08 | I36: 24476895 | J36: 6000 | K36: 9023 | N36: =SUM(K36:M36) -> 9023 | O36: =396794304-9023 -> 396785281 | P36: 28391932 | Q36: 440633 | R36: =SUM(O36:Q36) -> 425617846 | S36: 0 | T36: 0 | U36: 0 | V36: =F36+I36-P36-S36 -> 0 | W36: =G36+J36-M36-Q36-T36 -> 0 | X36: =SUM(U36:W36) -> 0 | Y36: 0 | Z36: 396785281 | AA36: SHM | AB36: SHT | AC36: Lunas | AD36: Lelang KPKNL | AQ36: 0 | AR36: =SUM(AE36:AQ36) -> 0
A37: 34 | B37: 02.300620 | C37: Ni Putu Novi Wulandari | D37: 1 | E37: 9.8497513e+08 | F37: 16416252 | G37: 1713215.3 | H37: =SUM(E37:G37) -> 1.0031046e+09 | I37: 0 | J37: 0 | K37: 41566056 | N37: =SUM(K37:M37) -> 41566056 | O37: 51000000 | P37: 0 | Q37: 0 | R37: =SUM(O37:Q37) -> 51000000 | S37: 0 | T37: 0 | U37: =E37-K37-O37 -> 8.9240908e+08 | V37: =F37+I37-P37-S37 -> 16416252 | W37: =G37+J37-M37-Q37-T37 -> 1713215.3 | X37: =SUM(U37:W37) -> 9.1053854e+08 | Y37: 1034000000 | Z37: 943409077 | AA37: SHM | AB37: SHT | AC37: Belum Lunas | AD37: Cessie | AQ37: 1.7848182e+08 | AR37: =SUM(AE37:AQ37) -> 1.7848182e+08 | AT37: =AR37/U37 -> 0.2
A38: 35 | B38: 02.300186 | C38: I Ketut Minsana | D38: 1 | E38: 52500000 | F38: 844375 | G38: 0 | H38: =SUM(E38:G38) -> 53344375 | I38: 2266572 | J38: 366240 | K38: 245322 | N38: =SUM(K38:M38) -> 245322 | O38: =52500000-245322 -> 52254678 | P38: 3110947 | Q38: 366240 | R38: =SUM(O38:Q38) -> 55731865 | S38: 0 | T38: 0 | U38: =E38-K38-O38 -> 0 | V38: =F38+I38-P38-S38 -> 0 | W38: =G38+J38-M38-Q38-T38 -> 0 | X38: =SUM(U38:W38) -> 0 | Y38: 0 | Z38: 52329906 | AA38: SHM | AB38: SHT | AC38: Lunas | AD38: Lelang KPKNL | AQ38: 0 | AR38: =SUM(AE38:AQ38) -> 0
A39: 36 | B39: 02.200245 | C39: Sebe Adi Putra I Made | D39: 1 | E39: 146066688 | F39: 832580 | G39: 0 | H39: =SUM(E39:G39) -> 146899268 | I39: 4810463 | J39: 4697955 | K39: 587161 | N39: =SUM(K39:M39) -> 587161 | O39: 145479527 | P39: 5643043 | Q39: 4697955 | R39: =SUM(O39:Q39) -> 155820525 | S39: 0 | T39: 0 | U39: =E39-K39-O39 -> 0 | V39: =F39+I39-P39-S39 -> 0 | W39: =G39+J39-M39-Q39-T39 -> 0 | X39: =SUM(U39:W39) -> 0 | Y39: 0 | Z39: 145479527 | AA39: SHM | AB39: SHT | AC39: Lunas | AD39: Lelang KPKNL | AQ39: 0 | AR39: =SUM(AE39:AQ39) -> 0
A40: 37 | B40: 02.200345 | C40: Dwinata Yudistira Putra | D40: 1 | E40: 3.2569071e+08 | F40: 5824435 | G40: 0 | H40: =SUM(E40:G40) -> 3.3151515e+08 | I40: 7623875 | J40: 450610 | K40: 0 | N40: =SUM(K40:M40) -> 0 | O40: 3.2569071e+08 | P40: 13448310 | Q40: 450610 | R40: =SUM(O40:Q40) -> 3.3958963e+08 | S40: 0 | T40: 0 | U40: =E40-K40-O40 -> 0 | V40: =F40+I40-P40-S40 -> 0 | W40: =G40+J40-M40-Q40-T40 -> 0 | X40: =SUM(U40:W40) -> 0 | Y40: 0 | Z40: 325690712 | AA40: SHM | AB40: SHT | AC40: Lunas | AD40: Lelang KPKNL | AQ40: 0 | AR40: =SUM(AE40:AQ40) -> 0
A41: 38 | B41: 02.200321 | C41: I Gede Andriawan Dusak | D41: 1 | E41: 1.2614077e+09 | F41: 8549478 | G41: 1.5994968e+08 | H41: =SUM(E41:G41) -> 1.4299068e+09 | I41: 0 | J41: 0 | K41: 0 | N41: =SUM(K41:M41) -> 0 | O41: 62410000 | P41: 0 | Q41: 0 | R41: =SUM(O41:Q41) -> 62410000 | S41: 0 | T41: 0 | U41: =E41-K41-O41 -> 1.1989977e+09 | V41: =F41+I41-P41-S41 -> 8549478 | W41: =G41+J41-M41-Q41-T41 -> 1.5994968e+08 | X41: =SUM(U41:W41) -> 1.3674968e+09 | Y41: 766000000 | Z41: 766000000 | AA41: SHM | AB41: SHT | AC41: Belum Lunas | AD41: Lelang KPKNL | AG41: 766000000 | AQ41: 0 | AR41: =SUM(AE41:AQ41) -> 766000000
A42: 39 | B42: 02.100346 | C42: Made Ayu Ima Pradasari | D42: 1 | E42: 35129811 | F42: 1087092 | G42: 63399095 | H42: =SUM(E42:G42) -> 99615998 | I42: 1120796 | J42: 0 | K42: 8055 | N42: =SUM(K42:M42) -> 8055 | O42: =35129811-8055 -> 35121756 | P42: 2207888 | Q42: 19370328 | R42: =SUM(O42:Q42) -> 56699972 | S42: 0 | T42: 44028767 | U42: 0 | V42: =F42+I42-P42-S42 -> 0 | W42: =G42+J42-M42-Q42-T42 -> 0 | X42: =SUM(U42:W42) -> 0 | Y42: 0 | Z42: 35121756 | AA42: SHM | AB42: SHT | AC42: Lunas | AD42: Lelang KPKNL | AQ42: 0 | AR42: =SUM(AE42:AQ42) -> 0
A43: 40 | B43: 02.100429 | C43: I Gede Ketut Dinamika | D43: 1 | E43: 16590924 | F43: 1236268 | G43: 4606140 | H43: =SUM(E43:G43) -> 22433332 | I43: 300782 | J43: 181019 | K43: 0 | N43: =SUM(K43:M43) -> 0 | O43: 16590924 | P43: 1537050 | Q43: 4787159 | R43: =SUM(O43:Q43) -> 22915133 | S43: 0 | T43: 0 | U43: =E43-K43-O43 -> 0 | V43: =F43+I43-P43-S43 -> 0 | W43: =G43+J43-M43-Q43-T43 -> 0 | X43: =SUM(U43:W43) -> 0 | Y43: 0 | Z43: 16590924 | AA43: SHM | AB43: SHT | AC43: Lunas | AD43: Lelang KPKNL | AQ43: 0 | AR43: =SUM(AE43:AQ43) -> 0
A44: 41 | B44: 02.300499 | C44: I Nyoman Surawibawa | D44: 1 | E44: 1.9502661e+08 | F44: 1186480 | G44: 3522143 | H44: =SUM(E44:G44) -> 1.9973523e+08 | I44: 20785889 | J44: 2745190.6 | K44: 9023 | N44: =SUM(K44:M44) -> 9023 | O44: =195026607-9023 -> 195017584 | P44: 21972369 | Q44: 530168 | R44: =SUM(O44:Q44) -> 217520121 | S44: 0 | T44: 5737165.6 | U44: 0 | V44: =F44+I44-P44-S44 -> 0 | W44: =G44+J44-M44-Q44-T44 -> 0 | X44: =SUM(U44:W44) -> 0 | Y44: 0 | Z44: 195026607 | AA44: SHM | AB44: SHT | AC44: Lunas | AD44: Lelang KPKNL | AQ44: 0 | AR44: =SUM(AE44:AQ44) -> 0
A45: 42 | B45: 02.300512 | C45: I Nyoman Surawibawa | D45: 1 | E45: 67862250 | F45: 167394 | G45: 738410 | H45: =SUM(E45:G45) -> 68768054 | I45: 8031410 | J45: 92628 | K45: 0 | N45: =SUM(K45:M45) -> 0 | O45: 67862250 | P45: 8198804 | Q45: 831038 | R45: =SUM(O45:Q45) -> 76892092 | S45: 0 | T45: 0 | U45: =E45-K45-O45 -> 0 | V45: =F45+I45-P45-S45 -> 0 | W45: =G45+J45-M45-Q45-T45 -> 0 | X45: =SUM(U45:W45) -> 0 | Y45: 0 | Z45: 67862250 | AA45: SHM | AB45: SHT | AC45: Lunas | AD45: Lelang KPKNL | AQ45: 0 | AR45: =SUM(AE45:AQ45) -> 0
A46: 43 | B46: 02.300671 | C46: Ni Wayan Darmini | D46: 1 | E46: 6.8096585e+08 | F46: 12768110 | G46: 0 | H46: =SUM(E46:G46) -> 6.9373396e+08 | I46: 0 | J46: 0 | K46: 77255626 | N46: =SUM(K46:M46) -> 77255626 | O46: 18500000 | P46: 0 | Q46: 0 | R46: =SUM(O46:Q46) -> 18500000 | S46: 0 | T46: 0 | U46: =E46-K46-O46 -> 5.8521022e+08 | V46: =F46+I46-P46-S46 -> 12768110 | W46: =G46+J46-M46-Q46-T46 -> 0 | X46: =SUM(U46:W46) -> 5.9797833e+08 | Y46: 1161000000 | Z46: 555839350 | AA46: SHM | AB46: SHT | AC46: Belum Lunas | AD46: Cessie | AQ46: 1.1704204e+08 | AR46: =SUM(AE46:AQ46) -> 1.1704204e+08 | AT46: =AR46/U46 -> 0.2
A47: 44 | B47: 02.300682 | C47: Muhamad Sutioso | D47: 1 | E47: 1.4625658e+08 | F47: 1535694 | G47: 0 | H47: =SUM(E47:G47) -> 1.4779227e+08 | I47: 2958929 | J47: 7385499 | K47: 0 | N47: =SUM(K47:M47) -> 0 | O47: 1.4625658e+08 | P47: 4494623 | Q47: 7385499 | R47: =SUM(O47:Q47) -> 1.581367e+08 | S47: 0 | T47: 0 | U47: =E47-K47-O47 -> 0 | V47: =F47+I47-P47-S47 -> 0 | W47: =G47+J47-M47-Q47-T47 -> 0 | X47: =SUM(U47:W47) -> 0 | Y47: 0 | Z47: 146256578 | AA47: SHM | AB47: SHT | AC47: Lunas | AD47: Lelang KPKNL | AQ47: 0 | AR47: =SUM(AE47:AQ47) -> 0
A48: 45 | B48: 02.300699 | C48: Bambang Basuki | D48: 1 | E48: 1.4811913e+08 | F48: 0 | G48: 0 | H48: =SUM(E48:G48) -> 1.4811913e+08 | I48: 7864653 | J48: 7730019 | K48: 0 | N48: =SUM(K48:M48) -> 0 | O48: 1.4811913e+08 | P48: 7864653 | Q48: 7730019 | R48: =SUM(O48:Q48) -> 1.637138e+08 | S48: 0 | T48: 0 | U48: =E48-K48-O48 -> 0 | V48: =F48+I48-P48-S48 -> 0 | W48: =G48+J48-M48-Q48-T48 -> 0 | X48: =SUM(U48:W48) -> 0 | Y48: 0 | Z48: 148119127 | AA48: SHGB | AB48: SHT | AC48: Lunas | AD48: Lelang KPKNL | AQ48: 0 | AR48: =SUM(AE48:AQ48) -> 0
A49: 46 | B49: 02.300700 | C49: Ni Wayan Darmini | D49: 1 | E49: 2.9565142e+08 | F49: 6208679.7 | G49: 0 | H49: =SUM(E49:G49) -> 3.018601e+08 | I49: 0 | J49: 0 | K49: 34221982 | N49: =SUM(K49:M49) -> 34221982 | O49: 0 | P49: 0 | Q49: 0 | R49: =SUM(O49:Q49) -> 0 | S49: 0 | T49: 0 | U49: =E49-K49-O49 -> 2.6142944e+08 | V49: =F49+I49-P49-S49 -> 6208679.7 | W49: =G49+J49-M49-Q49-T49 -> 0 | X49: =SUM(U49:W49) -> 2.6763812e+08 | Y49: 0 | Z49: 295651421 | AA49: SHM | AB49: SHT | AC49: Belum Lunas | AD49: Cessie | AQ49: 52285888 | AR49: =SUM(AE49:AQ49) -> 52285888 | AT49: =AR49/U49 -> 0.2
A50: 47 | B50: 02.300722 | C50: Anak Agung Sagung Alit Ernawa | D50: 1 | E50: 2.8469801e+08 | F50: 5551611 | G50: 0 | H50: =SUM(E50:G50) -> 2.9024962e+08 | I50: 14185091 | J50: 1474630 | K50: 79044 | N50: =SUM(K50:M50) -> 79044 | O50: =284698012-79044 -> 284618968 | P50: 19736702 | Q50: 1474630 | R50: =SUM(O50:Q50) -> 305830300 | S50: 0 | T50: 0 | U50: 0 | V50: =F50+I50-P50-S50 -> 0 | W50: =G50+J50-M50-Q50-T50 -> 0 | X50: =SUM(U50:W50) -> 0 | Y50: 0 | Z50: 284618968 | AA50: SHM | AB50: SHT | AC50: Lunas | AD50: Lelang KPKNL | AQ50: 0 | AR50: =SUM(AE50:AQ50) -> 0
A51: 48 | B51: 02.300740 | C51: I Ketut Hary Wiguna | D51: 1 | E51: 1.7956767e+09 | F51: 42266563 | G51: 399385.82 | H51: =SUM(E51:G51) -> 1.8383427e+09 | I51: 0 | J51: 0 | K51: 9023 | N51: =SUM(K51:M51) -> 9023 | O51: 1331245746 | P51: 0 | Q51: 0 | R51: =SUM(O51:Q51) -> 1331245746 | S51: 0 | T51: 0 | U51: =E51-K51-O51 -> 4.6442197e+08 | V51: =F51+I51-P51-S51 -> 42266563 | W51: =G51+J51-M51-Q51-T51 -> 399385.82 | X51: =SUM(U51:W51) -> 5.0708792e+08 | Y51: 1352000000 | Z51: 1392000000 | AA51: SHM | AB51: SHT | AC51: Belum Lunas | AD51: Cessie | AQ51: 0 | AR51: =SUM(AE51:AQ51) -> 0 | AS51: Sudah dilakukan lelang namun agunan tidak mengcover seluruh kewajiban debitur
A52: 49 | B52: 02.300752 | C52: Ni Wayan Darmini | D52: 1 | E52: 5.9751771e+08 | F52: 11153664 | G52: 0 | H52: =SUM(E52:G52) -> 6.0867137e+08 | I52: 0 | J52: 0 | K52: 13648894 | N52: =SUM(K52:M52) -> 13648894 | O52: 0 | P52: 0 | Q52: 0 | R52: =SUM(O52:Q52) -> 0 | S52: 0 | T52: 0 | U52: =E52-K52-O52 -> 5.8386881e+08 | V52: =F52+I52-P52-S52 -> 11153664 | W52: =G52+J52-M52-Q52-T52 -> 0 | X52: =SUM(U52:W52) -> 5.9502248e+08 | Y52: 0 | Z52: 309509230 | AA52: SHM | AB52: SHT | AC52: Belum Lunas | AD52: Cessie | AQ52: 1.1677376e+08 | AR52: =SUM(AE52:AQ52) -> 1.1677376e+08 | AT52: =AR52/U52 -> 0.2
A53: 50 | B53: 02.200323 | C53: Wawan Setiawan | D53: 1 | E53: 78567624 | F53: 1018091 | G53: 31688331 | H53: =SUM(E53:G53) -> 1.1127405e+08 | I53: 4960255 | J53: 0 | K53: 2681417 | N53: =SUM(K53:M53) -> 2681417 | O53: =78567624-2681417 -> 75886207 | P53: 5978346 | Q53: 15183946 | R53: =SUM(O53:Q53) -> 97048499 | S53: 0 | T53: 16504385 | U53: 0 | V53: =F53+I53-P53-S53 -> 0 | W53: =G53+J53-M53-Q53-T53 -> 0 | X53: =SUM(U53:W53) -> 0 | Y53: 0 | Z53: 75886207 | AA53: SHM | AB53: SHT | AC53: Lunas | AD53: Lelang KPKNL | AQ53: 0 | AR53: =SUM(AE53:AQ53) -> 0
A54: 51 | B54: 02.200346 | C54: Dwinata Yudistira Putra | D54: 1 | E54: 3.6516838e+08 | F54: 6530428 | G54: 0 | H54: =SUM(E54:G54) -> 3.7169881e+08 | I54: 8547981 | J54: 498503 | K54: 0 | N54: =SUM(K54:M54) -> 0 | O54: 3.6516838e+08 | P54: 15078409 | Q54: 498503 | R54: =SUM(O54:Q54) -> 3.8074529e+08 | S54: 0 | T54: 0 | U54: =E54-K54-O54 -> 0 | V54: =F54+I54-P54-S54 -> 0 | W54: =G54+J54-M54-Q54-T54 -> 0 | X54: =SUM(U54:W54) -> 0 | Y54: 0 | Z54: 365168381 | AA54: SHM | AB54: Tidak Ada Pengikatan | AC54: Lunas | AD54: Penagihan Langsung | AQ54: 0 | AR54: =SUM(AE54:AQ54) -> 0
A55: 52 | B55: 02.200350 | C55: Ni Putu Suciati | D55: 1 | E55: 5.4844627e+08 | F55: 12313100 | G55: 0 | H55: =SUM(E55:G55) -> 5.6075937e+08 | I55: 0 | J55: 0 | K55: 14535714 | N55: =SUM(K55:M55) -> 14535714 | O55: 265000000 | P55: 0 | Q55: 0 | R55: =SUM(O55:Q55) -> 265000000 | S55: 0 | T55: 0 | U55: =E55-K55-O55 -> 2.6891056e+08 | V55: =F55+I55-P55-S55 -> 12313100 | W55: =G55+J55-M55-Q55-T55 -> 0 | X55: =SUM(U55:W55) -> 2.8122366e+08 | Y55: 500000000 | Z55: 533910557 | AA55: SHM | AB55: SHT | AC55: Belum Lunas | AD55: Take Over | AE55: 12894736 | AF55: 12894736 | AG55: 12894736 | AH55: 12894736 | AI55: 12894736 | AJ55: 12894736 | AK55: 12894736 | AL55: 12894736 | AM55: 12894736 | AN55: 12894736 | AO55: 12894736 | AP55: =U55-(SUM(AE55:AO55)) -> 1.2706846e+08 | AQ55: 0 | AR55: =SUM(AE55:AQ55) -> 2.6891056e+08
A56: 53 | B56: 02.200359 | C56: Masruh | D56: 1 | E56: 1.1886201e+09 | F56: 21256489 | G56: 0 | H56: =SUM(E56:G56) -> 1.2098766e+09 | I56: 7.5967952e+08 | J56: 2.9857102e+08 | K56: 5188049 | N56: =SUM(K56:M56) -> 5188049 | O56: 1.183432e+09 | P56: =20417970+298571020 -> 318988990 | Q56: 0 | R56: =SUM(O56:Q56) -> 1.502421e+09 | S56: 4.6194702e+08 | T56: 2.9857102e+08 | U56: =E56-K56-O56 -> 0 | V56: 0 | W56: =G56+J56-M56-Q56-T56 -> 0 | X56: =SUM(U56:W56) -> 0 | Y56: 1021000000 | Z56: 1054850000 | AA56: SHM | AB56: SHT | AC56: Lunas | AD56: Take Over | AQ56: 0 | AR56: =SUM(AE56:AQ56) -> 0
A57: 54 | B57: 02.200360 | C57: Noor Fikriyana Ruhyadi | D57: 1 | E57: 1.2890261e+08 | F57: 1203091 | G57: 0 | H57: =SUM(E57:G57) -> 1.301057e+08 | I57: 47947 | J57: 1006000 | K57: 47947 | N57: =SUM(K57:M57) -> 47947 | O57: =128902609.51-47947 -> 1.2885466e+08 | P57: 1251038 | Q57: 1006000 | R57: =SUM(O57:Q57) -> 1.311117e+08 | S57: 0 | T57: 0 | U57: =E57-K57-O57 -> 0 | V57: =F57+I57-P57-S57 -> 0 | W57: =G57+J57-M57-Q57-T57 -> 0 | X57: =SUM(U57:W57) -> 0 | Y57: 0 | Z57: 128854663 | AA57: SHM | AB57: SHT | AC57: Lunas | AD57: Lelang KPKNL | AQ57: 0 | AR57: =SUM(AE57:AQ57) -> 0
A58: 55 | B58: 02.100419 | C58: I Gede Arya Wiguna,S.Ag | D58: 1 | E58: 61936539 | F58: 763884 | G58: 0 | H58: =SUM(E58:G58) -> 62700423 | I58: 868577 | J58: 6000 | K58: 0 | N58: =SUM(K58:M58) -> 0 | O58: 61936539 | P58: 1632461 | Q58: 6000 | R58: =SUM(O58:Q58) -> 63575000 | S58: 0 | T58: 0 | U58: 0 | V58: =F58+I58-P58-S58 -> 0 | W58: =G58+J58-M58-Q58-T58 -> 0 | X58: =SUM(U58:W58) -> 0 | Y58: 0 | Z58: 61936539 | AA58: SHM | AB58: SHT | AC58: Lunas | AD58: Lelang KPKNL | AQ58: 0 | AR58: =SUM(AE58:AQ58) -> 0
A59: 56 | B59: 02.400099 | C59: Paulus Tjiptadi | D59: 1 | E59: 6.8406111e+08 | F59: 25111529 | G59: 2677633 | H59: =SUM(E59:G59) -> 7.1185027e+08 | I59: 215009372 | J59: 99644312 | K59: 9023 | N59: =SUM(K59:M59) -> 9023 | O59: =684061107-9023 -> 684052084 | P59: 25111529 | Q59: 2678387 | R59: =SUM(O59:Q59) -> 711842000 | S59: 215009372 | T59: 99643558 | U59: 0 | V59: =F59+I59-P59-S59 -> 0 | W59: =G59+J59-M59-Q59-T59 -> 0 | X59: =SUM(U59:W59) -> 0 | Y59: 891000000 | Z59: 684061107 | AA59: SHM | AB59: SHT | AC59: Lunas | AD59: Lelang KPKNL | AQ59: 0 | AR59: =SUM(AE59:AQ59) -> 0
A60: 57 | B60: 02.100406 | C60: I Wayan Gede Wahyudarma | D60: 2 | E60: 3.011229e+08 | F60: 2785386.8 | G60: 9898.98 | H60: =SUM(E60:G60) -> 3.0391818e+08 | I60: 0 | J60: 0 | K60: 9023 | N60: =SUM(K60:M60) -> 9023 | O60: 144202100 | P60: 0 | Q60: 0 | R60: =SUM(O60:Q60) -> 144202100 | S60: 0 | T60: 0 | U60: =E60-K60-O60 -> 1.5691178e+08 | V60: =F60+I60-P60-S60 -> 2785386.8 | W60: =G60+J60-M60-Q60-T60 -> 9898.98 | X60: =SUM(U60:W60) -> 1.5970706e+08 | Y60: 136000000 | Z60: 136000000 | AA60: SHM | AB60: SHT | AC60: Belum Lunas | AD60: Cessie | AQ60: 0 | AR60: =SUM(AE60:AQ60) -> 0 | AS60: Sudah dilakukan lelang namun agunan tidak mengcover seluruh kewajiban debitur
A61: 58 | B61: 02.100446 | C61: I Putu Januarimbawa | D61: 2 | E61: 2.332569e+09 | F61: 31489682 | G61: 0 | H61: =SUM(E61:G61) -> 2.3640587e+09 | I61: 0 | J61: 0 | K61: 0 | N61: =SUM(K61:M61) -> 0 | O61: 0 | P61: 0 | Q61: 0 | R61: =SUM(O61:Q61) -> 0 | S61: 0 | T61: 0 | U61: =E61-K61-O61 -> 2.332569e+09 | V61: =F61+I61-P61-S61 -> 31489682 | W61: =G61+J61-M61-Q61-T61 -> 0 | X61: =SUM(U61:W61) -> 2.3640587e+09 | Y61: 1694000000 | Z61: 1674000000 | AA61: SHM | AB61: SHT | AC61: Belum Lunas | AD61: Cessie | AQ61: 4.665138e+08 | AR61: =SUM(AE61:AQ61) -> 4.665138e+08 | AT61: =AR61/U61 -> 0.2
A62: 59 | B62: 02.100465 | C62: I Putu Januarimbawa | D62: 2 | E62: 1.8869304e+08 | F62: 2264316.5 | G62: 0 | H62: =SUM(E62:G62) -> 1.9095736e+08 | I62: 0 | J62: 0 | K62: 0 | N62: =SUM(K62:M62) -> 0 | O62: 0 | P62: 0 | Q62: 0 | R62: =SUM(O62:Q62) -> 0 | S62: 0 | T62: 0 | U62: =E62-K62-O62 -> 1.8869304e+08 | V62: =F62+I62-P62-S62 -> 2264316.5 | W62: =G62+J62-M62-Q62-T62 -> 0 | X62: =SUM(U62:W62) -> 1.9095736e+08 | Y62: 0 | Z62: 1 | AA62: SHM | AB62: Tidak Ada Pengikatan | AC62: Belum Lunas | AD62: Cessie | AQ62: 9434652 | AR62: =SUM(AE62:AQ62) -> 9434652 | AT62: =AR62/U62 -> 0.05
A63: 60 | B63: 02.100467 | C63: Putu Dika Paradiswara | D63: 2 | E63: 129000000 | F63: 8219664.8 | G63: 396806.67 | H63: =SUM(E63:G63) -> 1.3761647e+08 | I63: 0 | J63: 0 | K63: 0 | N63: =SUM(K63:M63) -> 0 | O63: 0 | P63: 0 | Q63: 0 | R63: =SUM(O63:Q63) -> 0 | S63: 0 | T63: 0 | U63: =E63-K63-O63 -> 129000000 | V63: =F63+I63-P63-S63 -> 8219664.8 | W63: =G63+J63-M63-Q63-T63 -> 396806.67 | X63: =SUM(U63:W63) -> 1.3761647e+08 | Y63: 0 | Z63: 1 | AA63: SHM | AB63: Tidak Ada Pengikatan | AC63: Belum Lunas | AD63: Cessie | AQ63: 6450000 | AR63: =SUM(AE63:AQ63) -> 6450000 | AT63: =AR63/U63 -> 0.05
A64: 61 | B64: 02.300540 | C64: Tjok Dwie Taraputera | D64: 2 | E64: 29491442 | F64: 1288554 | G64: 190742 | H64: =SUM(E64:G64) -> 30970738 | I64: 3106831 | J64: 1610368 | K64: 8060 | N64: =SUM(K64:M64) -> 8060 | O64: =29491442-8060 -> 29483382 | P64: 4395385 | Q64: 1801110 | R64: =SUM(O64:Q64) -> 35679877 | S64: 0 | T64: 0 | U64: =E64-K64-O64 -> 0 | V64: =F64+I64-P64-S64 -> 0 | W64: =G64+J64-M64-Q64-T64 -> 0 | X64: =SUM(U64:W64) -> 0 | Y64: 0 | Z64: 29483382 | AA64: SHM | AB64: Tidak Ada Pengikatan | AC64: Lunas | AD64: Penagihan Langsung | AQ64: 0 | AR64: =SUM(AE64:AQ64) -> 0
A65: 62 | B65: 02.300618 | C65: Voyensis Susilo Agum | D65: 2 | E65: 12703801 | F65: 11292.26 | G65: 0 | H65: =SUM(E65:G65) -> 12715093 | I65: 0 | J65: 0 | K65: 120750 | N65: =SUM(K65:M65) -> 120750 | O65: 7110445 | P65: 0 | Q65: 0 | R65: =SUM(O65:Q65) -> 7110445 | S65: 0 | T65: 0 | U65: =E65-K65-O65 -> 5472605.8 | V65: =F65+I65-P65-S65 -> 11292.26 | W65: =G65+J65-M65-Q65-T65 -> 0 | X65: =SUM(U65:W65) -> 5483898 | Y65: 0 | Z65: 3004445 | AA65: BPKB | AB65: Tidak Ada Pengikatan | AC65: Belum Lunas | AD65: Cessie | AQ65: 273630.29 | AR65: =SUM(AE65:AQ65) -> 273630.29 | AT65: =AR65/U65 -> 0.05
A66: 63 | B66: 02.300636 | C66: Rosa Olivia | D66: 2 | E66: 9.6093345e+08 | F66: 18736641 | G66: 6048494.8 | H66: =SUM(E66:G66) -> 9.8571858e+08 | I66: 3.7163819e+08 | J66: 1.8500662e+08 | K66: 510174 | N66: =SUM(K66:M66) -> 510174 | O66: 9.6042327e+08 | P66: 225016728 | Q66: 0 | R66: =SUM(O66:Q66) -> 1.18544e+09 | S66: 0 | T66: 0 | U66: 0 | V66: =F66+I66-P66-S66 -> 1.6535811e+08 | W66: =G66+J66-M66-Q66-T66 -> 1.9105511e+08 | X66: =SUM(U66:W66) -> 3.5641322e+08 | Y66: 1234000000 | Z66: 960423272 | AA66: SHM | AB66: SHT | AC66: Belum Lunas | AD66: Cessie | AQ66: 0 | AR66: =SUM(AE66:AQ66) -> 0 | AS66: Sudah dilakukan lelang namun agunan tidak mengcover seluruh kewajiban debitur
A67: 64 | B67: 02.300679 | C67: Trisaraswati | D67: 2 | E67: 2481117742 | F67: 1.4175902e+08 | G67: 64780613 | H67: =SUM(E67:G67) -> 2.6876574e+09 | I67: 0 | J67: 0 | K67: 4904983 | N67: =SUM(K67:M67) -> 4904983 | O67: 2476212759 | P67: 17739741 | Q67: 0 | R67: =O67+P67+Q67 -> 2493952500 | S67: 0 | T67: 0 | U67: 0 | V67: =F67+I67-P67-S67 -> 1.2401928e+08 | W67: =G67+J67-M67-Q67-T67 -> 64780613 | X67: =SUM(U67:W67) -> 1.887999e+08 | Y67: 2472000000 | Z67: 2472000000 | AA67: SHGB | AB67: SHT | AC67: Belum Lunas | AD67: Cessie | AQ67: 0 | AR67: =SUM(AE67:AQ67) -> 0 | AS67: Sudah dilakukan lelang namun agunan tidak mengcover seluruh kewajiban debitur
A68: 65 | B68: 02.300687 | C68: I Wayan Rustawan | D68: 2 | E68: 1.1726762e+09 | F68: 25505707 | G68: 0 | H68: =SUM(E68:G68) -> 1.1981819e+09 | I68: 0 | J68: 0 | K68: 0 | N68: =SUM(K68:M68) -> 0 | O68: 0 | P68: 0 | Q68: 0 | R68: =SUM(O68:Q68) -> 0 | S68: 0 | T68: 0 | U68: =E68-K68-O68 -> 1.1726762e+09 | V68: =F68+I68-P68-S68 -> 25505707 | W68: =G68+J68-M68-Q68-T68 -> 0 | X68: =SUM(U68:W68) -> 1.1981819e+09 | Y68: 2174000000 | Z68: 1172676197 | AA68: SHM | AB68: SHT | AC68: Belum Lunas | AD68: Cessie | AR68: =SUM(AE68:AQ68) -> 0 | AS68: Kredit Linkage (BPR Supra)
A69: 66 | B69: 02.300693 | C69: I Nyoman Ari Kusuma Artha | D69: 2 | E69: 71655792 | F69: 732481 | G69: 0 | H69: =SUM(E69:G69) -> 72388273 | I69: 10772920 | J69: 0 | K69: 31047 | N69: =SUM(K69:M69) -> 31047 | O69: =71655792-31047 -> 71624745 | P69: 9599435 | Q69: 0 | R69: =SUM(O69:Q69) -> 81224180 | S69: 1905966 | T69: 0 | U69: =E69-K69-O69 -> 0 | V69: =F69+I69-P69-S69 -> 0 | W69: =G69+J69-M69-Q69-T69 -> 0 | X69: =SUM(U69:W69) -> 0 | Y69: 0 | Z69: 71624745 | AA69: BPKB | AB69: Tidak Ada Pengikatan | AC69: Lunas | AD69: Penagihan Langsung | AQ69: 0 | AR69: =SUM(AE69:AQ69) -> 0
A70: 67 | B70: 02.300706 | C70: I Made Sukasna | D70: 2 | E70: 1.197379e+09 | F70: 77717397 | G70: 10363553 | H70: =SUM(E70:G70) -> 1.28546e+09 | I70: 0 | J70: 0 | K70: 9023 | N70: =SUM(K70:M70) -> 9023 | O70: 119600000 | P70: 0 | Q70: 0 | R70: =SUM(O70:Q70) -> 119600000 | S70: 0 | T70: 0 | U70: =E70-K70-O70 -> 1.07777e+09 | V70: =F70+I70-P70-S70 -> 77717397 | W70: =G70+J70-M70-Q70-T70 -> 10363553 | X70: =SUM(U70:W70) -> 1.1658509e+09 | Y70: 895000000 | Z70: 978600000 | AA70: SHM | AB70: SHT | AC70: Belum Lunas | AD70: Lelang KPKNL | AQ70: 895000000 | AR70: =SUM(AE70:AQ70) -> 895000000
A71: 68 | B71: 02.300713 | C71: Ida Ayu Made Ari Wahyuni | D71: 2 | E71: 798252675 | F71: 46084190 | G71: 4536521 | H71: =SUM(E71:G71) -> 848873386 | I71: 390440380 | J71: 261899978 | K71: 9023 | N71: =SUM(K71:M71) -> 9023 | O71: 798243652 | P71: 51756348 | Q71: 0 | R71: =SUM(O71:Q71) -> 850000000 | S71: 384768222 | T71: 266436499 | U71: =E71-K71-O71 -> 0 | V71: =F71+I71-P71-S71 -> 0 | W71: =G71+J71-M71-Q71-T71 -> 0 | X71: =SUM(U71:W71) -> 0 | Y71: 1165000000 | Z71: 798243652 | AA71: SHM | AB71: SHT | AC71: Lunas | AD71: Lelang KPKNL | AQ71: 0 | AR71: =SUM(AE71:AQ71) -> 0
A72: 69 | B72: 02.300730 | C72: Ratna Cynthia Lesmana | D72: 2 | E72: 12969223 | F72: 69169.08 | G72: 0 | H72: =SUM(E72:G72) -> 13038392 | I72: 0 | J72: 0 | K72: 41152 | N72: =SUM(K72:M72) -> 41152 | O72: 5000000 | P72: 0 | Q72: 0 | R72: =SUM(O72:Q72) -> 5000000 | S72: 0 | T72: 0 | U72: =E72-K72-O72 -> 7928071.4 | V72: =F72+I72-P72-S72 -> 69169.08 | W72: =G72+J72-M72-Q72-T72 -> 0 | X72: =SUM(U72:W72) -> 7997240.4 | Y72: 0 | Z72: 5000000 | AA72: BPKB | AB72: Tidak Ada Pengikatan | AC72: Belum Lunas | AD72: Cessie | AQ72: 396403.57 | AR72: =SUM(AE72:AQ72) -> 396403.57 | AT72: =AR72/U72 -> 0.05
A73: 70 | B73: 02.300733 | C73: I Gede Sutrisna | D73: 2 | E73: 2.3413615e+09 | F73: 7804538.2 | G73: 0 | H73: =SUM(E73:G73) -> 2.349166e+09 | I73: 0 | J73: 0 | K73: 3292221 | N73: =SUM(K73:M73) -> 3292221 | O73: 0 | P73: 0 | Q73: 0 | R73: =SUM(O73:Q73) -> 0 | S73: 0 | T73: 0 | U73: =E73-K73-O73 -> 2.3380692e+09 | V73: =F73+I73-P73-S73 -> 7804538.2 | W73: =G73+J73-M73-Q73-T73 -> 0 | X73: =SUM(U73:W73) -> 2.3458738e+09 | Y73: 1552000000 | Z73: 1552000000 | AA73: SHM | AB73: SHT | AC73: Belum Lunas | AD73: Cessie | AQ73: 4.6761385e+08 | AR73: =SUM(AE73:AQ73) -> 4.6761385e+08 | AT73: =AR73/U73 -> 0.2
A74: 71 | B74: 02.300739 | C74: Komang Robhy Suardika | D74: 2 | E74: 1.978754e+09 | F74: 2532214.3 | G74: 250010.74 | H74: =SUM(E74:G74) -> 1.9815362e+09 | I74: 0 | J74: 0 | K74: 44089112 | N74: =SUM(K74:M74) -> 44089112 | O74: 5000000 | P74: 0 | Q74: 0 | R74: =SUM(O74:Q74) -> 5000000 | S74: 0 | T74: 0 | U74: =E74-K74-O74 -> 1.9296648e+09 | V74: =F74+I74-P74-S74 -> 2532214.3 | W74: =G74+J74-M74-Q74-T74 -> 250010.74 | X74: =SUM(U74:W74) -> 1.9324471e+09 | Y74: 2411000000 | Z74: 1934664845 | AA74: SHM | AB74: SHT | AC74: Belum Lunas | AD74: Lelang KPKNL | AP74: 1.9324471e+09 | AQ74: 0 | AR74: =SUM(AE74:AQ74) -> 1.9324471e+09
A75: 72 | B75: 02.300747 | C75: I Ketut Tangkas Budidarma | D75: 2 | E75: 1.4980781e+09 | F75: 43604298 | G75: 551824.65 | H75: =SUM(E75:G75) -> 1.5422343e+09 | I75: 0 | J75: 0 | K75: 9023 | N75: =SUM(K75:M75) -> 9023 | O75: 0 | P75: 0 | Q75: 0 | R75: =SUM(O75:Q75) -> 0 | S75: 0 | T75: 0 | U75: =E75-K75-O75 -> 1.4980691e+09 | V75: =F75+I75-P75-S75 -> 43604298 | W75: =G75+J75-M75-Q75-T75 -> 551824.65 | X75: =SUM(U75:W75) -> 1.5422252e+09 | Y75: 1007000000 | Z75: 751000000 | AA75: SHM | AB75: SHT | AC75: Belum Lunas | AD75: Lelang KPKNL | AH75: 1007000000 | AQ75: 0 | AR75: =SUM(AE75:AQ75) -> 1007000000
A76: 73 | B76: 02.300749 | C76: I Wayan Rustawan | D76: 2 | E76: 5.9691853e+08 | F76: 11639911 | G76: 0 | H76: =SUM(E76:G76) -> 6.0855844e+08 | I76: 0 | J76: 0 | K76: 0 | N76: =SUM(K76:M76) -> 0 | O76: 0 | P76: 0 | Q76: 0 | R76: =SUM(O76:Q76) -> 0 | S76: 0 | T76: 0 | U76: =E76-K76-O76 -> 5.9691853e+08 | V76: =F76+I76-P76-S76 -> 11639911 | W76: =G76+J76-M76-Q76-T76 -> 0 | X76: =SUM(U76:W76) -> 6.0855844e+08 | Y76: 0 | Z76: 1 | AA76: SHM | AB76: Tidak Ada Pengikatan | AC76: Belum Lunas | AD76: Cessie | AQ76: 29845927 | AR76: =SUM(AE76:AQ76) -> 29845927 | AT76: =AR76/U76 -> 0.05
A77: 74 | B77: 02.400103 | C77: Ni Putu Adnyani | D77: 2 | E77: 4.9830719e+08 | F77: 26035586 | G77: 1023110.1 | H77: =SUM(E77:G77) -> 5.2536588e+08 | I77: 0 | J77: 0 | K77: 8167 | N77: =SUM(K77:M77) -> 8167 | O77: 391547100 | P77: 0 | Q77: 0 | R77: =SUM(O77:Q77) -> 391547100 | S77: 0 | T77: 0 | U77: =E77-K77-O77 -> 1.0675192e+08 | V77: =F77+I77-P77-S77 -> 26035586 | W77: =G77+J77-M77-Q77-T77 -> 1023110.1 | X77: =SUM(U77:W77) -> 1.3381062e+08 | Y77: 372000000 | Z77: 372000000 | AA77: SHM | AB77: SHT | AC77: Belum Lunas | AD77: Cessie | AQ77: 21350384 | AR77: =SUM(AE77:AQ77) -> 21350384 | AT77: =AR77/U77 -> 0.2
A78: 75 | B78: 02.400104 | C78: I Ketut Sudra | D78: 2 | E78: 516250000 | F78: 36567708 | G78: 2893275 | H78: =SUM(E78:G78) -> 5.5571098e+08 | I78: 0 | J78: 0 | K78: 0 | N78: =SUM(K78:M78) -> 0 | O78: 0 | P78: 0 | Q78: 0 | R78: =SUM(O78:Q78) -> 0 | S78: 0 | T78: 0 | U78: =E78-K78-O78 -> 516250000 | V78: =F78+I78-P78-S78 -> 36567708 | W78: =G78+J78-M78-Q78-T78 -> 2893275 | X78: =SUM(U78:W78) -> 5.5571098e+08 | Y78: 0 | Z78: 1 | AA78: SHM | AB78: Tidak Ada Pengikatan | AC78: Belum Lunas | AD78: Cessie | AQ78: 25812500 | AR78: =SUM(AE78:AQ78) -> 25812500 | AT78: =AR78/U78 -> 0.05
A79: 76 | B79: 02.200343 | C79: Ni Nyoman Anggareni | D79: 2 | E79: 0 | F79: 99601 | G79: 1082656 | H79: =SUM(E79:G79) -> 1182257 | I79: 0 | J79: 20961 | K79: 0 | N79: =SUM(K79:M79) -> 0 | O79: 0 | P79: 99601 | Q79: 1103617 | R79: =SUM(O79:Q79) -> 1203218 | S79: 0 | T79: 0 | U79: =E79-K79-O79 -> 0 | V79: =F79+I79-P79-S79 -> 0 | W79: =G79+J79-M79-Q79-T79 -> 0 | X79: =SUM(U79:W79) -> 0 | Y79: 0 | Z79: 0 | AA79: SHM | AB79: Tidak Ada Pengikatan | AC79: Lunas | AD79: Penagihan Langsung | AQ79: 0 | AR79: =SUM(AE79:AQ79) -> 0
A80: 77 | B80: 02.100456 | C80: Anak Agung Gede Wiranatha | D80: 2 | E80: 7.3720031e+08 | F80: 89762678 | G80: 26612674 | H80: =SUM(E80:G80) -> 8.5357566e+08 | I80: 0 | J80: 0 | K80: 0 | N80: =SUM(K80:M80) -> 0 | O80: 0 | P80: 0 | Q80: 0 | R80: =SUM(O80:Q80) -> 0 | S80: 0 | T80: 0 | U80: =E80-K80-O80 -> 7.3720031e+08 | V80: =F80+I80-P80-S80 -> 89762678 | W80: =G80+J80-M80-Q80-T80 -> 26612674 | X80: =SUM(U80:W80) -> 8.5357566e+08 | Y80: 1722000000 | Z80: 1 | AA80: SHGB | AB80: SHT | AC80: Belum Lunas | AD80: Cessie | AQ80: 1.4744006e+08 | AR80: =SUM(AE80:AQ80) -> 1.4744006e+08 | AT80: =AR80/U80 -> 0.2
A81: 78 | B81: 02.300471 | C81: I Gusti Made Pujayasa | D81: 2 | E81: 125384008 | F81: 8851068 | G81: 12831669 | H81: =SUM(E81:G81) -> 147066745 | I81: 3627481.4 | J81: 1929232 | K81: 8051 | N81: =SUM(K81:M81) -> 8051 | O81: =125384008-8051 -> 125375957 | P81: 12478549 | Q81: 14760901 | R81: =SUM(O81:Q81) -> 1.5261541e+08 | S81: 0 | T81: 0 | U81: =E81-K81-O81 -> 0 | V81: =F81+I81-P81-S81 -> 0 | W81: =G81+J81-M81-Q81-T81 -> 0 | X81: =SUM(U81:W81) -> 0 | Y81: 0 | Z81: 125375957 | AA81: SHGB | AB81: SHT | AC81: Lunas | AD81: Lelang KPKNL | AQ81: 0 | AR81: =SUM(AE81:AQ81) -> 0
A82: 79 | B82: 02.300613 | C82: Ida Ayu Komang Manik Trisnawa | D82: 2 | E82: 983888891 | F82: 1.2591716e+08 | G82: 23727939 | H82: =SUM(E82:G82) -> 1.133534e+09 | I82: 0 | J82: 0 | K82: 0 | N82: =SUM(K82:M82) -> 0 | O82: 0 | P82: 0 | Q82: 0 | R82: =SUM(O82:Q82) -> 0 | S82: 0 | T82: 0 | U82: =E82-K82-O82 -> 983888891 | V82: =F82+I82-P82-S82 -> 1.2591716e+08 | W82: =G82+J82-M82-Q82-T82 -> 23727939 | X82: =SUM(U82:W82) -> 1.133534e+09 | Y82: 0 | Z82: 9.8388889e+08 | AA82: SHM | AB82: SHT | AC82: Belum Lunas | AD82: Cessie | AQ82: 1.9677778e+08 | AR82: =SUM(AE82:AQ82) -> 1.9677778e+08 | AT82: =AR82/U82 -> 0.2
A83: 80 | B83: 02.300634 | C83: Wayan Arda Chandra | D83: 2 | E83: 1258640966 | F83: 117488221 | G83: 66529915 | H83: =SUM(E83:G83) -> 1.4426591e+09 | I83: 0 | J83: 0 | K83: 0 | N83: =SUM(K83:M83) -> 0 | O83: 1258640966 | P83: 84018136 | Q83: 0 | R83: =SUM(O83:Q83) -> 1342659102 | S83: 33470085 | T83: 66529915 | U83: =E83-K83-O83 -> 0 | V83: =F83+I83-P83-S83 -> 0 | W83: =G83+J83-M83-Q83-T83 -> 0 | X83: =SUM(U83:W83) -> 0 | Y83: 0 | Z83: 1258640966 | AA83: SHM | AB83: SHT | AC83: Lunas | AD83: Lelang KPKNL | AQ83: 0 | AR83: =SUM(AE83:AQ83) -> 0
A84: 81 | B84: 02.300750 | C84: Raden Ajeng Koesramadhani | D84: 2 | E84: 450000000 | F84: 38788909 | G84: 2858949 | H84: =SUM(E84:G84) -> 4.9164786e+08 | I84: 0 | J84: 0 | K84: 0 | N84: =SUM(K84:M84) -> 0 | O84: 0 | P84: 0 | Q84: 0 | R84: =SUM(O84:Q84) -> 0 | S84: 0 | T84: 0 | U84: =E84-K84-O84 -> 450000000 | V84: =F84+I84-P84-S84 -> 38788909 | W84: =G84+J84-M84-Q84-T84 -> 2858949 | X84: =SUM(U84:W84) -> 4.9164786e+08 | Y84: 0 | Z84: 1 | AA84: SHM | AB84: Tidak Ada Pengikatan | AC84: Belum Lunas | AD84: Cessie | AQ84: 22500000 | AR84: =SUM(AE84:AQ84) -> 22500000 | AT84: =AR84/U84 -> 0.05
A85: 82 | B85: 02.100457 | C85: Putu Dika Paradiswara | D85: 3 | E85: 1.1452676e+09 | F85: 74610057 | G85: 12319408 | H85: =SUM(E85:G85) -> 1.2321971e+09 | I85: 0 | J85: 0 | K85: 0 | N85: =SUM(K85:M85) -> 0 | O85: 0 | P85: 0 | Q85: 0 | R85: =SUM(O85:Q85) -> 0 | S85: 0 | T85: 0 | U85: =E85-K85-O85 -> 1.1452676e+09 | V85: =F85+I85-P85-S85 -> 74610057 | W85: =G85+J85-M85-Q85-T85 -> 12319408 | X85: =SUM(U85:W85) -> 1.2321971e+09 | Y85: 852000000 | Z85: 852000000 | AA85: SHM | AB85: SHT | AC85: Belum Lunas | AD85: Cessie | AQ85: 2.2905352e+08 | AR85: =SUM(AE85:AQ85) -> 2.2905352e+08 | AT85: =AR85/U85 -> 0.2
A86: 83 | B86: 02.200307 | C86: I Gst Nyoman Santhi | D86: 3 | E86: 447058133 | F86: 23340545 | G86: 86725962 | H86: =SUM(E86:G86) -> 557124640 | I86: 0 | J86: 0 | K86: 0 | N86: =SUM(K86:M86) -> 0 | O86: 447058133 | P86: 10340545 | Q86: 36726351 | R86: =SUM(O86:Q86) -> 494125029 | S86: 13000000 | T86: 49999611 | U86: =E86-K86-O86 -> 0 | V86: =F86+I86-P86-S86 -> 0 | W86: =G86+J86-M86-Q86-T86 -> 0 | X86: =SUM(U86:W86) -> 0 | Y86: 0 | Z86: 4.4705813e+08 | AA86: SHM | AB86: SHT | AC86: Lunas | AD86: Lelang KPKNL | AQ86: 0 | AR86: =SUM(AE86:AQ86) -> 0
A87: 84 | B87: 02.200354 | C87: I Made Sugita | D87: 3 | E87: 645498544 | F87: 46625408 | G87: 2938579 | H87: =SUM(E87:G87) -> 695062531 | I87: 302535567 | J87: 224658096 | K87: 7444 | N87: =SUM(K87:M87) -> 7444 | O87: 645491100 | P87: 54508900 | Q87: 0 | R87: =SUM(O87:Q87) -> 700000000 | S87: 294652075 | T87: 227596675 | U87: =E87-K87-O87 -> 0 | V87: =F87+I87-P87-S87 -> 0 | W87: =G87+J87-M87-Q87-T87 -> 0 | X87: =SUM(U87:W87) -> 0 | Y87: 1399000000 | Z87: 645491100 | AA87: SHM | AB87: SHT | AC87: Lunas | AD87: Lelang KPKNL | AQ87: 0 | AR87: =SUM(AE87:AQ87) -> 0
A88: 85 | B88: 02.200355 | C88: I Gusti Nyoman Santhi | D88: 3 | E88: 99295314 | F88: 3903413 | G88: 516243.88 | H88: =SUM(E88:G88) -> 1.0371497e+08 | I88: 0 | J88: 0 | K88: 0 | N88: =SUM(K88:M88) -> 0 | O88: 99295314 | P88: 3903413 | Q88: 516243.88 | R88: =SUM(O88:Q88) -> 1.0371497e+08 | S88: 0 | T88: 0 | U88: =E88-K88-O88 -> 0 | V88: =F88+I88-P88-S88 -> 0 | W88: =G88+J88-M88-Q88-T88 -> 0 | X88: =SUM(U88:W88) -> 0 | Y88: 0 | Z88: 99295314 | AA88: SHM | AB88: Tidak Ada Pengikatan | AC88: Lunas | AD88: Penagihan Langsung | AQ88: 0 | AR88: =SUM(AE88:AQ88) -> 0
A89: 86 | B89: 02.300185 | C89: Lestari Ni Gusti Putu | D89: 3 | E89: 1.4693583e+08 | F89: 9185136 | G89: 38463624 | H89: =SUM(E89:G89) -> 1.9458459e+08 | I89: 5337335.3 | J89: 1620421 | K89: 48280 | N89: =SUM(K89:M89) -> 48280 | O89: =146935826.67-48280 -> 1.4688755e+08 | P89: 14522471 | Q89: 40084045 | R89: =SUM(O89:Q89) -> 2.0149406e+08 | S89: 0 | T89: 0 | U89: =E89-K89-O89 -> 0 | V89: =F89+I89-P89-S89 -> 0 | W89: =G89+J89-M89-Q89-T89 -> 0 | X89: =SUM(U89:W89) -> 0 | Y89: 0 | Z89: 146887547 | AA89: SHGB | AB89: SHT | AC89: Lunas | AD89: Lelang KPKNL | AQ89: 0 | AR89: =SUM(AE89:AQ89) -> 0
A90: 87 | B90: 02.300658 | C90: Ni Made Ari Cahyanti | D90: 3 | E90: 977504605 | F90: 70804630 | G90: 27136300 | H90: =SUM(E90:G90) -> 1.0754455e+09 | I90: 3.4960362e+08 | J90: 1.9016941e+08 | K90: 0 | N90: =SUM(K90:M90) -> 0 | O90: 977504605 | P90: 70804630 | Q90: 8312593.1 | R90: =SUM(O90:Q90) -> 1.0566218e+09 | S90: 349603621 | T90: 2.0899312e+08 | U90: =E90-K90-O90 -> 0 | V90: =F90+I90-P90-S90 -> 0 | W90: =G90+J90-M90-Q90-T90 -> 0 | X90: =SUM(U90:W90) -> 0 | Y90: 875000000 | Z90: 875000000 | AA90: SHGB | AB90: SHT | AC90: Lunas | AD90: Lelang KPKNL | AQ90: 0 | AR90: =SUM(AE90:AQ90) -> 0
A91: 88 | B91: 02.300684 | C91: Ni Nyoman Jelih | D91: 3 | E91: 2.4380524e+09 | F91: 1.7002746e+08 | G91: 14793318 | H91: =SUM(E91:G91) -> 2.6228732e+09 | I91: 0 | J91: 0 | K91: 8052 | N91: =SUM(K91:M91) -> 8052 | O91: 37000000 | P91: 0 | Q91: 0 | R91: =SUM(O91:Q91) -> 37000000 | S91: 0 | T91: 0 | U91: =E91-K91-O91 -> 2.4010443e+09 | V91: =F91+I91-P91-S91 -> 1.7002746e+08 | W91: =G91+J91-M91-Q91-T91 -> 14793318 | X91: =SUM(U91:W91) -> 2.5858651e+09 | Y91: 3795000000 | Z91: 2438044329 | AA91: SHM | AB91: SHT | AC91: Belum Lunas | AD91: Lelang KPKNL | AI91: 2.5858651e+09 | AQ91: 0 | AR91: =SUM(AE91:AQ91) -> 2.5858651e+09
A92: 89 | B92: 02.300725 | C92: I Gusti Ayu Arwati | D92: 3 | E92: 6.4666174e+08 | F92: 55124667 | G92: 4283616.6 | H92: =SUM(E92:G92) -> 7.0607003e+08 | I92: 0 | J92: 0 | K92: 7082 | N92: =SUM(K92:M92) -> 7082 | O92: 0 | P92: 0 | Q92: 0 | R92: =SUM(O92:Q92) -> 0 | S92: 0 | T92: 0 | U92: =E92-K92-O92 -> 6.4665466e+08 | V92: =F92+I92-P92-S92 -> 55124667 | W92: =G92+J92-M92-Q92-T92 -> 4283616.6 | X92: =SUM(U92:W92) -> 7.0606294e+08 | Y92: 758000000 | Z92: 646654660 | AA92: SHM | AB92: SHT | AC92: Belum Lunas | AD92: Cessie | AQ92: 1.2933093e+08 | AR92: =SUM(AE92:AQ92) -> 1.2933093e+08 | AT92: =AR92/U92 -> 0.2
A93: 90 | B93: 02.300732 | C93: I Made Astawa | D93: 3 | E93: 1.9897284e+09 | F93: 1.4077832e+08 | G93: 8561570.2 | H93: =SUM(E93:G93) -> 2.1390683e+09 | I93: 0 | J93: 0 | K93: 8055 | N93: =SUM(K93:M93) -> 8055 | O93: 0 | P93: 0 | Q93: 0 | R93: =SUM(O93:Q93) -> 0 | S93: 0 | T93: 0 | U93: =E93-K93-O93 -> 1.9897204e+09 | V93: =F93+I93-P93-S93 -> 1.4077832e+08 | W93: =G93+J93-M93-Q93-T93 -> 8561570.2 | X93: =SUM(U93:W93) -> 2.1390603e+09 | Y93: 1208000000 | Z93: 1208000000 | AA93: SHM | AB93: SHT | AC93: Belum Lunas | AD93: Lelang KPKNL | AK93: 1208000000 | AQ93: 0 | AR93: =SUM(AE93:AQ93) -> 1208000000
A94: 91 | B94: 02.300741 | C94: Poppy Eunike Nany Kustiani | D94: 3 | E94: 1.286023e+09 | F94: 77177785 | G94: 4793731.2 | H94: =SUM(E94:G94) -> 1.3679945e+09 | I94: 0 | J94: 0 | K94: 8055 | N94: =SUM(K94:M94) -> 8055 | O94: 0 | P94: 0 | Q94: 0 | R94: =SUM(O94:Q94) -> 0 | S94: 0 | T94: 0 | U94: =E94-K94-O94 -> 1.2860149e+09 | V94: =F94+I94-P94-S94 -> 77177785 | W94: =G94+J94-M94-Q94-T94 -> 4793731.2 | X94: =SUM(U94:W94) -> 1.3679864e+09 | Y94: 1387000000 | Z94: 1286014896 | AA94: SHM | AB94: SHT | AC94: Belum Lunas | AD94: Cessie | AQ94: 2.5720298e+08 | AR94: =SUM(AE94:AQ94) -> 2.5720298e+08 | AT94: =AR94/U94 -> 0.2
A95: 92 | B95: 02.300745 | C95: Ni Made Ari Cahyanti | D95: 3 | E95: 224420261 | F95: 17147006 | G95: 1810904.8 | H95: =SUM(E95:G95) -> 2.4337817e+08 | I95: 84997823 | J95: 51166470 | K95: 0 | N95: =SUM(K95:M95) -> 0 | O95: 224420261 | P95: 17147006 | Q95: 1810904.8 | R95: =SUM(O95:Q95) -> 2.4337817e+08 | S95: 84997823 | T95: 51166470 | U95: =E95-K95-O95 -> 0 | V95: =F95+I95-P95-S95 -> 0 | W95: =G95+J95-M95-Q95-T95 -> 0 | X95: =SUM(U95:W95) -> 0 | Y95: 0 | Z95: 1 | AA95: SHGB | AB95: Tidak Ada Pengikatan | AC95: Lunas | AD95: Penagihan Langsung | AQ95: 0 | AR95: =SUM(AE95:AQ95) -> 0
A96: 93 | B96: 02.300748 | C96: I Gusti Ngurah Adi Putra | D96: 3 | E96: 2195494187 | F96: 1.4305755e+08 | G96: 10777671 | H96: =SUM(E96:G96) -> 2.3493294e+09 | I96: 0 | J96: 0 | K96: 8055 | N96: =SUM(K96:M96) -> 8055 | O96: 1313095000 | P96: 0 | Q96: 0 | R96: =SUM(O96:Q96) -> 1313095000 | S96: 0 | T96: 0 | U96: =E96-K96-O96 -> 882391132 | V96: =F96+I96-P96-S96 -> 1.4305755e+08 | W96: =G96+J96-M96-Q96-T96 -> 10777671 | X96: =SUM(U96:W96) -> 1.0362264e+09 | Y96: 1262000000 | Z96: 1262000000 | AA96: SHM | AB96: SHT | AC96: Belum Lunas | AD96: Lelang KPKNL | AE96: 1262000000 | AQ96: 0 | AR96: =SUM(AE96:AQ96) -> 1262000000
A97: 94 | B97: 02.400089 | C97: I Ketut Sudra | D97: 3 | E97: 972222232 | F97: 74506713 | G97: 3.0550221e+08 | H97: =SUM(E97:G97) -> 1.3522312e+09 | I97: 0 | J97: 0 | K97: 0 | N97: =SUM(K97:M97) -> 0 | O97: 0 | P97: 0 | Q97: 0 | R97: =SUM(O97:Q97) -> 0 | S97: 0 | T97: 0 | U97: =E97-K97-O97 -> 972222232 | V97: =F97+I97-P97-S97 -> 74506713 | W97: =G97+J97-M97-Q97-T97 -> 3.0550221e+08 | X97: =SUM(U97:W97) -> 1.3522312e+09 | Y97: 0 | Z97: 9.7222223e+08 | AA97: SHM | AB97: SHT | AC97: Belum Lunas | AD97: Cessie | AQ97: 1.9444445e+08 | AR97: =SUM(AE97:AQ97) -> 1.9444445e+08 | AT97: =AR97/U97 -> 0.2
A98: 95 | B98: 02.400101 | C98: Ida Ayu Putu Yustini | D98: 3 | E98: 1191689625 | F98: 65804684 | G98: 3163176 | H98: =SUM(E98:G98) -> 1260657485 | I98: 8055 | J98: 0 | K98: 8055 | N98: =SUM(K98:M98) -> 8055 | O98: =1191689625-8055 -> 1191681570 | P98: 15155255 | Q98: 3163176 | R98: =SUM(O98:Q98) -> 1210000001 | S98: 50657484 | T98: 0 | U98: =E98-K98-O98 -> 0 | V98: =F98+I98-P98-S98 -> 0 | W98: =G98+J98-M98-Q98-T98 -> 0 | X98: =SUM(U98:W98) -> 0 | Y98: 0 | Z98: 1191681570 | AA98: SHM | AB98: SHT | AC98: Lunas | AD98: Lelang KPKNL | AQ98: 0 | AR98: =SUM(AE98:AQ98) -> 0
A99: 96 | B99: 02.200329 | C99: I Agus Nuaba Putra | D99: 3 | E99: 4.3484061e+08 | F99: 22818852 | G99: 2900236.5 | H99: =SUM(E99:G99) -> 4.605597e+08 | I99: 0 | J99: 0 | K99: 0 | N99: =SUM(K99:M99) -> 0 | O99: 0 | P99: 0 | Q99: 0 | R99: =SUM(O99:Q99) -> 0 | S99: 0 | T99: 0 | U99: =E99-K99-O99 -> 4.3484061e+08 | V99: =F99+I99-P99-S99 -> 22818852 | W99: =G99+J99-M99-Q99-T99 -> 2900236.5 | X99: =SUM(U99:W99) -> 4.605597e+08 | Y99: 987000000 | Z99: 4.3484061e+08 | AA99: SHM | AB99: SHT | AC99: Belum Lunas | AD99: Cessie | AQ99: 86968122 | AR99: =SUM(AE99:AQ99) -> 86968122 | AT99: =AR99/U99 -> 0.2
A100: 97 | B100: 02.200358 | C100: I Agus Nuaba Putra | D100: 3 | E100: 89392952 | F100: 5106060.5 | G100: 763108.81 | H100: =SUM(E100:G100) -> 95262121 | I100: 0 | J100: 0 | K100: 0 | N100: =SUM(K100:M100) -> 0 | O100: 0 | P100: 0 | Q100: 0 | R100: =SUM(O100:Q100) -> 0 | S100: 0 | T100: 0 | U100: =E100-K100-O100 -> 89392952 | V100: =F100+I100-P100-S100 -> 5106060.5 | W100: =G100+J100-M100-Q100-T100 -> 763108.81 | X100: =SUM(U100:W100) -> 95262121 | Y100: 0 | Z100: 89392952 | AA100: SHM | AB100: Tidak Ada Pengikatan | AC100: Belum Lunas | AD100: Cessie | AQ100: 4469647.6 | AR100: =SUM(AE100:AQ100) -> 4469647.6
A101: 98 | B101: 02.200316 | C101: Ni Nyoman Anggareni | D101: 3 | E101: 4.8359561e+08 | F101: 57239724 | G101: 47864228 | H101: =SUM(E101:G101) -> 5.8869956e+08 | I101: 0 | J101: 0 | K101: 0 | N101: =SUM(K101:M101) -> 0 | O101: 2796782.5 | P101: 0 | Q101: 0 | R101: =SUM(O101:Q101) -> 2796782.5 | S101: 0 | T101: 0 | U101: =E101-K101-O101 -> 4.8079883e+08 | V101: =F101+I101-P101-S101 -> 57239724 | W101: =G101+J101-M101-Q101-T101 -> 47864228 | X101: =SUM(U101:W101) -> 5.8590278e+08 | Y101: 886000000 | Z101: 4.8359561e+08 | AA101: SHM | AB101: SHT | AC101: Belum Lunas | AD101: Cessie | AQ101: 96159766 | AR101: =SUM(AE101:AQ101) -> 96159766
...

Sheet Resume Kredit
A3: Row Labels | B3: Count of Nama Debitur | C3: Sum of Baki Debet (NP Audited) | D3: Sum of Setoff Pokok | E3: Sum of Pencairan Pokok s.d Mei 2021 | F3: Sum of Sisa Kewajiban Pokok Mei 2021 | G3: Sum of LANAP
A4: Belum Lunas | B4: 120 | C4: 1.0550826e+11 | D4: 3.4377527e+08 | E4: 1.4682665e+10 | F4: 9.048182e+10 | G4: 8.1143591e+10
A5: 1 | B5: 13 | C5: 8.1738587e+09 | D5: 1.8143095e+08 | E5: 2.4599068e+09 | F5: 5.5325209e+09 | G5: 6.7057287e+09
A6: 2 | B6: 19 | C6: 1.8389923e+10 | D6: 52993628 | E6: 4.1090957e+09 | F6: 1.4227834e+10 | G6: 1.2995258e+10
A7: 3 | B7: 13 | C7: 1.4180757e+10 | D7: 39299 | E7: 1.3528918e+09 | F7: 1.2827826e+10 | G7: 1.2024772e+10
A8: 4 | B8: 75 | C8: 6.4763721e+10 | D8: 109311391 | E8: 6.7607707e+09 | F8: 5.7893639e+10 | G8: 49417832431
A9: Lunas | B9: 76 | C9: 2.1445688e+10 | D9: 80383442 | E9: 2.1365304e+10 | F9: 0 | G9: 2.0186988e+10
A10: 1 | B10: 43 | C10: 6.561002e+09 | D10: 64476662 | E10: 6.4965254e+09 | F10: 0 | G10: 6.2849566e+09
A11: 2 | B11: 6 | C11: 2283424883 | D11: 56181 | E11: 2283368702 | F11: 0 | G11: 2283368702
A12: 3 | B12: 8 | C12: 4.2574023e+09 | D12: 63779 | E12: 4.2573385e+09 | F12: 0 | G12: 3.4054137e+09
A13: 4 | B13: 19 | C13: 8.3438584e+09 | D13: 15786820 | E13: 8.3280716e+09 | F13: 0 | G13: 8213248885
A14: Grand Total | B14: 196 | C14: 1.2695395e+11 | D14: 4.2415871e+08 | E14: 3.6047969e+10 | F14: 9.048182e+10 | G14: 1.0133058e+11
A16: Keterangan | B16: Kol. | C16: Jumlah Debitur | D16: Baki Debet (NP Audited) | E16: Setoff Pokok | F16: Pencairan s.d. Mei 2021 | G16: Sisa Kewajiban Pokok s.d. Mei 2021
A17: (1) | B17: (2) | C17: (3) | D17: (4) | E17: (5) | F17: (6) | G17: (7) = (4) - (5) - (6)
A18: Belum Lunas | B18: 1 | C18: 13 | D18: 8.1738587e+09 | E18: 1.8143095e+08 | F18: 2.4599068e+09 | G18: =D18-E18-F18 -> 5.5325209e+09
B19: 2 | C19: 19 | D19: 1.8389923e+10 | E19: 52993628 | F19: 4.1090957e+09 | G19: =D19-E19-F19 -> 1.4227834e+10
B20: 3 | C20: 13 | D20: 1.4180757e+10 | E20: 39299 | F20: 1.3528918e+09 | G20: =D20-E20-F20 -> 1.2827826e+10
B21: 4 | C21: 75 | D21: 6.4763721e+10 | E21: 109311391 | F21: 6.7607707e+09 | G21: =D21-E21-F21 -> 5.7893639e+10
A22: Subtotal | C22: =SUM(C18:C21) -> 120 | D22: =SUM(D18:D21) -> 1.0550826e+11 | E22: =SUM(E18:E21) -> 3.4377527e+08 | F22: =SUM(F18:F21) -> 1.4682665e+10 | G22: =SUM(G18:G21) -> 9.048182e+10
A23: Lunas | B23: 1 | C23: 43 | D23: 6.561002e+09 | E23: 64476662 | F23: 6.4965254e+09 | G23: 0
B24: 2 | C24: 6 | D24: 2283424883 | E24: 56181 | F24: 2283368702 | G24: =D24-E24-F24 -> 0
B25: 3 | C25: 8 | D25: 4.2574023e+09 | E25: 63779 | F25: 4.2573385e+09 | G25: =D25-E25-F25 -> 0
B26: 4 | C26: 19 | D26: 8.3438584e+09 | E26: 15786820 | F26: 8.3280716e+09 | G26: =D26-E26-F26 -> 0
A27: Subtotal | C27: =SUM(C23:C26) -> 76 | D27: =SUM(D23:D26) -> 2.1445688e+10 | E27: =SUM(E23:E26) -> 80383442 | F27: =SUM(F23:F26) -> 2.1365304e+10 | G27: =SUM(G23:G26) -> 0
A28: Grand Total | C28: =C22+C27 -> 196 | D28: =D22+D27 -> 1.2695395e+11 | E28: =E22+E27 -> 4.2415871e+08 | F28: =F22+F27 -> 3.6047969e+10 | G28: =G22+G27 -> 9.048182e+10
A31: Row Labels | B31: Count of Nama Debitur | C31: Sum of Baki Debet (NP Audited) | D31: Sum of Setoff Pokok | E31: Sum of Pencairan Pokok s.d Mei 2021 | F31: Sum of Sisa Kewajiban Pokok Mei 2021 | I31: Kol. | J31: Jenis Agunan | K31: Jenis Pengikatan | L31: Jumlah Debitur | M31: Baki Debet (NP Audited) | N31: Setoff Pokok | O31: Pencairan s.d. Mei 2021 | P31: Sisa Kewajiban Pokok s.d. Mei 2021
A32: Belum Lunas | B32: 120 | C32: 1.0550826e+11 | D32: 3.4377527e+08 | E32: 1.4682665e+10 | F32: 9.048182e+10 | I32: (1) | J32: (2) | K32: (3) | L32: (4) | M32: (5) | N32: (6) | O32: (7) | P32: (8) = (5) - (6) - (7)
A33: 1 | B33: 13 | C33: 8.1738587e+09 | D33: 1.8143095e+08 | E33: 2.4599068e+09 | F33: 5.5325209e+09 | I33: 1 | J33: BPKB | K33: Tidak Ada Pengikatan | L33: 1 | M33: 45345152 | N33: 63773 | O33: 12172098 | P33: 33109281
A34: BPKB | B34: 1 | C34: 45345152 | D34: 63773 | E34: 12172098 | F34: 33109281 | J34: SHM | K34: SHT | L34: 12 | M34: 8.1285136e+09 | N34: 1.8136718e+08 | O34: 2447734749 | P34: 5.4994116e+09
A35: Tidak Ada Pengikatan | B35: 1 | C35: 45345152 | D35: 63773 | E35: 12172098 | F35: 33109281 | L35: =SUM(L33:L34) -> 13 | M35: =SUM(M33:M34) -> 8.1738587e+09 | N35: =SUM(N33:N34) -> 1.8143095e+08 | O35: =SUM(O33:O34) -> 2.4599068e+09 | P35: =SUM(P33:P34) -> 5.5325209e+09
A36: SHM | B36: 12 | C36: 8.1285136e+09 | D36: 1.8136718e+08 | E36: 2447734749 | F36: 5.4994116e+09 | I36: 2 | J36: BPKB | K36: Tidak Ada Pengikatan | L36: 2 | M36: 25673024 | N36: 161902 | O36: 12110445 | P36: 13400677
A37: SHT | B37: 12 | C37: 8.1285136e+09 | D37: 1.8136718e+08 | E37: 2447734749 | F37: 5.4994116e+09 | J37: SHGB | K37: SHT | L37: 2 | M37: 3.218318e+09 | N37: 4904983 | O37: 2476212759 | P37: 7.3720031e+08
A38: 2 | B38: 19 | C38: 1.8389923e+10 | D38: 52993628 | E38: 4.1090957e+09 | F38: 1.4227834e+10 | J38: SHM | K38: SHT | L38: 10 | M38: 1.326507e+10 | N38: 47926743 | O38: 1.6207725e+09 | P38: 1.1596371e+10
A39: BPKB | B39: 2 | C39: 25673024 | D39: 161902 | E39: 12110445 | F39: 13400677 | K39: Tidak Ada Pengikatan | L39: 5 | M39: 1.8808616e+09 | N39: 0 | O39: 0 | P39: 1.8808616e+09
A40: Tidak Ada Pengikatan | B40: 2 | C40: 25673024 | D40: 161902 | E40: 12110445 | F40: 13400677 | L40: =SUM(L36:L39) -> 19 | M40: =SUM(M36:M39) -> 1.8389923e+10 | N40: =SUM(N36:N39) -> 52993628 | O40: =SUM(O36:O39) -> 4.1090957e+09 | P40: =SUM(P36:P39) -> 1.4227834e+10
A41: SHGB | B41: 2 | C41: 3.218318e+09 | D41: 4904983 | E41: 2476212759 | F41: 7.3720031e+08 | I41: 3 | J41: SHM | K41: SHT | L41: 10 | M41: 1.3667048e+10 | N41: 39299 | O41: 1.3528918e+09 | P41: 1.2314117e+10
A42: SHT | B42: 2 | C42: 3.218318e+09 | D42: 4904983 | E42: 2476212759 | F42: 7.3720031e+08 | J42: SHM | K42: Tidak Ada Pengikatan | L42: 3 | M42: 5.1370907e+08 | N42: 0 | O42: 0 | P42: 5.1370907e+08
A43: SHM | B43: 15 | C43: 1.5145932e+10 | D43: 47926743 | E43: 1.6207725e+09 | F43: 1.3477233e+10 | L43: =SUM(L41:L42) -> 13 | M43: =SUM(M41:M42) -> 1.4180757e+10 | N43: =SUM(N41:N42) -> 39299 | O43: =SUM(O41:O42) -> 1.3528918e+09 | P43: =SUM(P41:P42) -> 1.2827826e+10
A44: SHT | B44: 10 | C44: 1.326507e+10 | D44: 47926743 | E44: 1.6207725e+09 | F44: 1.1596371e+10 | I44: 4 | J44: KTA | K44: Tidak Ada Pengikatan | L44: 1 | M44: 5.9892996e+08 | N44: 104230918 | O44: 0 | P44: 4.9469904e+08
A45: Tidak Ada Pengikatan | B45: 5 | C45: 1.8808616e+09 | D45: 0 | E45: 0 | F45: 1.8808616e+09 | J45: SHGB | K45: SHT | L45: 2 | M45: 2.2893714e+09 | N45: 0 | O45: 526679600 | P45: 1.7626918e+09
A46: 3 | B46: 13 | C46: 1.4180757e+10 | D46: 39299 | E46: 1.3528918e+09 | F46: 1.2827826e+10 | K46: Tidak Ada Pengikatan | L46: 1 | M46: 1.9794439e+09 | N46: 0 | O46: 0 | P46: 1.9794439e+09
A47: SHM | B47: 13 | C47: 1.4180757e+10 | D47: 39299 | E47: 1.3528918e+09 | F47: 1.2827826e+10 | J47: SHM | K47: SHT | L47: 48 | M47: 5.1132523e+10 | N47: 5080473 | O47: 6.1930911e+09 | P47: 4.4934352e+10
A48: SHT | B48: 10 | C48: 1.3667048e+10 | D48: 39299 | E48: 1.3528918e+09 | F48: 1.2314117e+10 | K48: SKMHT | L48: 1 | M48: 39474394 | N48: 0 | O48: 0 | P48: 39474394
A49: Tidak Ada Pengikatan | B49: 3 | C49: 5.1370907e+08 | D49: 0 | E49: 0 | F49: 5.1370907e+08 | K49: Tidak Ada Pengikatan | L49: 22 | M49: 8.7239784e+09 | N49: 0 | O49: 41000000 | P49: 8.6829784e+09
A50: 4 | B50: 75 | C50: 6.4763721e+10 | D50: 109311391 | E50: 6.7607707e+09 | F50: 5.7893639e+10 | L50: =SUM(L44:L49) -> 75 | M50: =SUM(M44:M49) -> 6.4763721e+10 | N50: =SUM(N44:N49) -> 109311391 | O50: =SUM(O44:O49) -> 6.7607707e+09 | P50: =SUM(P44:P49) -> 5.7893639e+10
A51: KTA | B51: 1 | C51: 5.9892996e+08 | D51: 104230918 | E51: 0 | F51: 4.9469904e+08 | L51: =L50+L43+L40+L35 -> 120 | M51: =M50+M43+M40+M35 -> 1.0550826e+11 | N51: =N50+N43+N40+N35 -> 3.4377527e+08 | O51: =O50+O43+O40+O35 -> 1.4682665e+10 | P51: =P50+P43+P40+P35 -> 9.048182e+10
A52: Tidak Ada Pengikatan | B52: 1 | C52: 5.9892996e+08 | D52: 104230918 | E52: 0 | F52: 4.9469904e+08
A53: SHGB | B53: 3 | C53: 4.2688153e+09 | D53: 0 | E53: 526679600 | F53: 3.7421357e+09
A54: SHT | B54: 2 | C54: 2.2893714e+09 | D54: 0 | E54: 526679600 | F54: 1.7626918e+09
A55: Tidak Ada Pengikatan | B55: 1 | C55: 1.9794439e+09 | D55: 0 | E55: 0 | F55: 1.9794439e+09
A56: SHM | B56: 71 | C56: 5.9895976e+10 | D56: 5080473 | E56: 6.2340911e+09 | F56: 5.3656804e+10
A57: SHT | B57: 48 | C57: 5.1132523e+10 | D57: 5080473 | E57: 6.1930911e+09 | F57: 4.4934352e+10
A58: SKMHT | B58: 1 | C58: 39474394 | D58: 0 | E58: 0 | F58: 39474394
A59: Tidak Ada Pengikatan | B59: 22 | C59: 8.7239784e+09 | D59: 0 | E59: 41000000 | F59: 8.6829784e+09
A60: Lunas | B60: 76 | C60: 2.1445688e+10 | D60: 80383442 | E60: 2.1365304e+10 | F60: 0
A61: 1 | B61: 43 | C61: 6.561002e+09 | D61: 64476662 | E61: 6.4965254e+09 | F61: 0
A62: BPKB | B62: 10 | C62: 2.1888852e+08 | D62: 409289 | E62: 2.1847923e+08 | F62: 0
A63: Tidak Ada Pengikatan | B63: 10 | C63: 2.1888852e+08 | D63: 409289 | E63: 2.1847923e+08 | F63: 0
A64: SHGB | B64: 1 | C64: 1.4811913e+08 | D64: 0 | E64: 1.4811913e+08 | F64: 0
A65: SHT | B65: 1 | C65: 1.4811913e+08 | D65: 0 | E65: 1.4811913e+08 | F65: 0
A66: SHM | B66: 32 | C66: 6.1939944e+09 | D66: 64067373 | E66: 6.129927e+09 | F66: 0
A67: SHT | B67: 27 | C67: 5.6836155e+09 | D67: 63934924 | E67: 5.6196806e+09 | F67: 0
A68: SKMHT | B68: 2 | C68: 37429148 | D68: 0 | E68: 37429148 | F68: 0
A69: Tidak Ada Pengikatan | B69: 3 | C69: 4.7294968e+08 | D69: 132449 | E69: 4.7281723e+08 | F69: 0
A70: 2 | B70: 6 | C70: 2283424883 | D70: 56181 | E70: 2283368702 | F70: 0
A71: BPKB | B71: 1 | C71: 71655792 | D71: 31047 | E71: 71624745 | F71: 0
A72: Tidak Ada Pengikatan | B72: 1 | C72: 71655792 | D72: 31047 | E72: 71624745 | F72: 0
A73: SHGB | B73: 1 | C73: 125384008 | D73: 8051 | E73: 125375957 | F73: 0
A74: SHT | B74: 1 | C74: 125384008 | D74: 8051 | E74: 125375957 | F74: 0
A75: SHM | B75: 4 | C75: 2086385083 | D75: 17083 | E75: 2086368000 | F75: 0
A76: SHT | B76: 2 | C76: 2056893641 | D76: 9023 | E76: 2056884618 | F76: 0
A77: Tidak Ada Pengikatan | B77: 2 | C77: 29491442 | D77: 8060 | E77: 29483382 | F77: 0
A78: 3 | B78: 8 | C78: 4.2574023e+09 | D78: 63779 | E78: 4.2573385e+09 | F78: 0
A79: SHGB | B79: 3 | C79: 1.3488607e+09 | D79: 48280 | E79: 1.3488124e+09 | F79: 0
A80: SHT | B80: 2 | C80: 1.1244404e+09 | D80: 48280 | E80: 1.1243922e+09 | F80: 0
A81: Tidak Ada Pengikatan | B81: 1 | C81: 224420261 | D81: 0 | E81: 224420261 | F81: 0
A82: SHM | B82: 5 | C82: 2.9085416e+09 | D82: 15499 | E82: 2.9085261e+09 | F82: 0
A83: SHT | B83: 3 | C83: 2284246302 | D83: 15499 | E83: 2284230803 | F83: 0
A84: Tidak Ada Pengikatan | B84: 2 | C84: 6.2429531e+08 | D84: 0 | E84: 6.2429531e+08 | F84: 0
A85: 4 | B85: 19 | C85: 8.3438584e+09 | D85: 15786820 | E85: 8.3280716e+09 | F85: 0
A86: SHGB | B86: 1 | C86: 290021334 | D86: 15026616 | E86: 274994718 | F86: 0
A87: SHT | B87: 1 | C87: 290021334 | D87: 15026616 | E87: 274994718 | F87: 0
A88: SHM | B88: 18 | C88: 8.0538371e+09 | D88: 760204 | E88: 8.0530769e+09 | F88: 0
A89: SHT | B89: 16 | C89: 7.0674625e+09 | D89: 753124 | E89: 7.0667093e+09 | F89: 0
A90: Tidak Ada Pengikatan | B90: 2 | C90: 986374596 | D90: 7080 | E90: 986367516 | F90: 0
A91: Grand Total | B91: 196 | C91: 1.2695395e+11 | D91: 4.2415871e+08 | E91: 3.6047969e+10 | F91: 9.048182e+10

Sheet Tanah dan Bangunan
A1: No. | B1: Kode Aset | C1: Uraian | D1: Saldo (NP Audited) | E1: Saldo (LANAP) | F1: Realisasi Pencairan | G1: Nilai Aset yang Belum Dicairkan | H1: Keterangan (Cair/Belum Dicairkan) | I1: Strategi Pencairan | J1: Kendala Pencairan | K1: 44348 | L1: 44378 | M1: 44409 | N1: 44440 | O1: 44470 | P1: 44501 | Q1: 44531 | R1: 44562 | S1: 44593 | T1: 44621 | U1: 44652 | V1: 44682 | W1: 44713 | X1: Total
A2: 1 | C2: Gedung Kantor Pusat Denpasar Jl. Gajah Mada No. 125 sd 127 | D2: 10000000000 | E2: 11318100000 | F2: 0 | G2: =D2 -> 10000000000 | H2: Belum Cair | I2: Penjualan Langsung | J2: Kondisi Perekomian Bali pasca Pandemi | Q2: 5763901874 | X2: =SUM(K2:W2) -> 5763901874
A3: 2 | C3: Gedung Kantor Cabang Tabanan Jl Ngurah Rai No. 97 | D3: 1210718850 | E3: 1089000000 | F3: 1177270000 | G3: 0 | H3: Cair | I3: - | X3: =SUM(K3:W3) -> 0
D4: =SUM(D2:D3) -> 11210718850 | E4: =SUM(E2:E3) -> 12407100000 | F4: =SUM(F2:F3) -> 1177270000 | G4: =SUM(G2:G3) -> 10000000000 | K4: =SUM(K2:K3) -> 0 | L4: =SUM(L2:L3) -> 0 | M4: =SUM(M2:M3) -> 0 | N4: =SUM(N2:N3) -> 0 | O4: =SUM(O2:O3) -> 0 | P4: =SUM(P2:P3) -> 0 | Q4: =SUM(Q2:Q3) -> 5763901874 | R4: =SUM(R2:R3) -> 0 | ... W4: =SUM(W2:W3) -> 0 | X4: =SUM(K4:W4) -> 5763901874

Sheet Kendaraan
A1: No. | B1: Kode Aset | C1: Uraian | D1: Saldo (NP Audited) | E1: Saldo (LANAP) | F1: Realisasi Pencairan s.d. Mei 2021 | G1: Nilai Aset yang Belum Dicairkan | H1: Keterangan (Cair/Belum Dicairkan) | I1: Strategi Pencairan | J1: Kendala Pencairan | K1: 44348 | L1: 44378 | M1: 44409 | N1: 44440 | O1: 44470 | P1: 44501 | Q1: 44531 | R1: 44562 | S1: 44593 | T1: 44621 | U1: 44652 | V1: 44682 | W1: 44713 | X1: Total
A2: 1 | C2: Mobil Alpard DK1092JE | D2: 490539000 | E2: 300000000 | F2: 300000000 | H2: Cair | X2: =SUM(K2:W2) -> 0
A3: 2 | C3: Mobil Alpard DK1473XG | D3: 361736601 | E3: 200000000 | F3: 200000000 | H3: Cair | X3: =SUM(K3:W3) -> 0
A4: 3 | C4: Mobil Inova(DK 1349 GJ) | D4: 220250016 | E4: 117200000 | F4: 117200000 | H4: Cair | X4: =SUM(K4:W4) -> 0
A5: 4 | C5: Mobil Inova | D5: 271950000 | E5: 156000000 | F5: 156000000 | H5: Cair | X5: =SUM(K5:W5) -> 0
A6: 5 | C6: Mobil Inova | D6: 271950000 | E6: 156000000 | F6: 156000000 | H6: Cair | X6: =SUM(K6:W6) -> 0
A7: 6 | C7: Mobil Avanza | D7: 174200000 | E7: 124000000 | F7: 124000000 | H7: Cair | X7: =SUM(K7:W7) -> 0
A8: 7 | C8: Mobil Avanza | D8: 174200000 | E8: 124000000 | F8: 124000000 | H8: Cair | X8: =SUM(K8:W8) -> 0
A9: 8 | C9: Mobil Avanza | D9: 174200000 | E9: 124000000 | F9: 124000000 | H9: Cair | X9: =SUM(K9:W9) -> 0
A10: 9 | C10: Mobil Avanza | D10: 174200000 | E10: 85000000 | F10: 0 | G10: =D10 -> 174200000 | H10: Belum Cair | I10: Penjualan Langsung | T10: 85000000 | X10: =SUM(K10:W10) -> 85000000
A11: 10 | C11: Sepeda Motor Revo | D11: 12190000 | E11: 4150000 | F11: 4150000 | H11: Cair | X11: =SUM(K11:W11) -> 0
A12: 11 | C12: Sepeda Motor Honda Revo | D12: 11940000 | E12: 4000000 | F12: 4000000 | H12: Cair | X12: =SUM(K12:W12) -> 0
A13: 12 | C13: Sepeda Motor Supra X | D13: 14420000 | E13: 3750000 | F13: 3750000 | H13: Cair | X13: =SUM(K13:W13) -> 0
A14: 13 | C14: Sepeda Motor Yamaha Mio | D14: 0 | E14: 5100000 | F14: 5100000 | H14: Cair | X14: =SUM(K14:W14) -> 0
A15: 14 | C15: Sepeda Motor Honda Vario | D15: 0 | E15: 9166666.7 | F15: 0 | G15: 0 | H15: Belum Cair | I15: Penjualan Langsung | T15: 9200000 | X15: =SUM(K15:W15) -> 9200000
D16: =SUM(D2:D15) -> 2351775617 | E16: =SUM(E2:E15) -> 1.4123667e+09 | F16: =SUM(F2:F15) -> 1318200000 | G16: =SUM(G2:G15) -> 174200000 | K16: =SUM(K2:K15) -> 0 | L16: =SUM(L2:L15) -> 0 | M16: =SUM(M2:M15) -> 0 | N16: =SUM(N2:N15) -> 0 | O16: =SUM(O2:O15) -> 0 | P16: =SUM(P2:P15) -> 0 | Q16: =SUM(Q2:Q15) -> 0 | R16: =SUM(R2:R15) -> 0 | ... X16: =SUM(X2:X15) -> 94200000

Sheet Inventaris
A1: No. | B1: Kode Aset | C1: Uraian | D1: Saldo (NP Audited) | E1: Saldo (LANAP) | F1: Realisasi Pencairan s.d. Mei 2021 | G1: Nilai Aset yang Belum Dicairkan | H1: Keterangan (Cair/Belum Dicairkan) | I1: Strategi Pencairan | J1: 44348 | K1: 44378 | L1: 44409 | M1: 44440 | N1: 44470 | O1: 44501 | P1: 44531 | Q1: 44562 | R1: 44593 | S1: 44621 | T1: 44652 | U1: 44682 | V1: 44713 | W1: Total
A2: 1 | C2: Lukisan Gatsu | D2: 50000000 | E2: 3600000 | F2: 0 | G2: =D2 -> 50000000 | H2: Belum Cair | I2: Penjualan Langsung/Lelang | O2: 3600000 | W2: =SUM(J2:V2) -> 3600000
A3: 2 | C3: Lukisan Gatsu | D3: 50000000 | E3: 1575000 | F3: 0 | G3: =D3 -> 50000000 | H3: Belum Cair | I3: Penjualan Langsung/Lelang | O3: 1575000 | W3: =SUM(J3:V3) -> 1575000
A4: 3 | C4: Lukisan Gatsu | D4: 25000000 | E4: 1125000 | F4: 0 | G4: =D4 -> 25000000 | H4: Belum Cair | I4: Penjualan Langsung/Lelang | O4: 1125000 | W4: =SUM(J4:V4) -> 1125000
A5: 4 | C5: Lukisan Gatsu | D5: 10000000 | E5: 450000 | F5: 0 | G5: =D5 -> 10000000 | H5: Belum Cair | I5: Penjualan Langsung/Lelang | O5: 450000 | W5: =SUM(J5:V5) -> 450000
A6: 5 | C6: Lukisan Gatsu | D6: 15000000 | E6: 1125000 | F6: 0 | G6: =D6 -> 15000000 | H6: Belum Cair | I6: Penjualan Langsung/Lelang | O6: 1125000 | W6: =SUM(J6:V6) -> 1125000
A7: 6 | C7: Lukisan Lantai 3 Kpo | D7: 7000000 | E7: 900000 | F7: 0 | G7: =D7 -> 7000000 | H7: Belum Cair | I7: Penjualan Langsung/Lelang | O7: 900000 | W7: =SUM(J7:V7) -> 900000
A8: 7 | C8: Lukisan R.Komisaris | D8: 10000000 | E8: 450000 | F8: 0 | G8: =D8 -> 10000000 | H8: Belum Cair | I8: Penjualan Langsung/Lelang | O8: 450000 | W8: =SUM(J8:V8) -> 450000
A9: 8 | C9: Kursi Sapi Gatsu | D9: 5000000 | E9: 280000 | F9: 300000 | H9: Cair
A10: 9 | C10: Karpet Zebra Kulit Sapi Kk Gatsu | D10: 5000000 | E10: 772000 | F10: 800000 | H10: Cair
A11: 10 | C11: Lukisan R. Komisaris | D11: 10000000 | E11: 495000 | F11: 0 | G11: =D11 -> 10000000 | H11: Belum Cair | I11: Penjualan Langsung/Lelang | O11: 495000 | W11: =SUM(J11:V11) -> 495000
A12: 11 | C12: Sofa Besar R. Komisaris | D12: 4000000 | E12: 616000 | F12: 0 | G12: =D12 -> 4000000 | H12: Belum Cair | I12: Penjualan Langsung/Lelang | O12: 616000 | W12: =SUM(J12:V12) -> 616000
A13: 12 | C13: Jam R. Komisaris | D13: 3500000 | E13: 540000 | F13: 0 | G13: =D13 -> 3500000 | H13: Belum Cair | I13: Penjualan Langsung/Lelang | O13: 540000 | W13: =SUM(J13:V13) -> 540000
A14: 13 | C14: Kursi Kotak Sapi | D14: 5000000 | E14: 432000 | F14: 450000 | H14: Cair
A15: 14 | C15: Cermin Teller Kpo | D15: 5000000 | E15: 772000 | F15: 0 | G15: =D15 -> 5000000 | H15: Belum Cair | I15: Penjualan Langsung/Lelang | O15: 772000 | W15: =SUM(J15:V15) -> 772000
A16: 15 | C16: Lukisan Accounting Kpo | D16: 1500000 | E16: 450000 | F16: 0 | G16: =D16 -> 1500000 | H16: Belum Cair | I16: Penjualan Langsung/Lelang | O16: 450000 | W16: =SUM(J16:V16) -> 450000
A17: 16 | C17: Kursi Komisaris | D17: 3000000 | E17: 464000 | F17: 0 | G17: =D17 -> 3000000 | H17: Belum Cair | I17: Penjualan Langsung/Lelang | O17: 464000 | W17: =SUM(J17:V17) -> 464000
A18: 17 | C18: Lukisan Kom Kpo | D18: 2500000 | E18: 675000 | F18: 0 | G18: =D18 -> 2500000 | H18: Belum Cair | I18: Penjualan Langsung/Lelang | O18: 675000 | W18: =SUM(J18:V18) -> 675000
A19: 18 | C19: Lukisan R. Dirut Kpo | D19: 5000000 | E19: 675000 | F19: 0 | G19: =D19 -> 5000000 | H19: Belum Cair | I19: Penjualan Langsung/Lelang | O19: 675000 | W19: =SUM(J19:V19) -> 675000
A20: 19 | C20: Lukisan R. Hrd | D20: 1500000 | E20: 225000 | F20: 0 | G20: =D20 -> 1500000 | H20: Belum Cair | I20: Penjualan Langsung/Lelang | O20: 225000 | W20: =SUM(J20:V20) -> 225000
A21: 20 | C21: Lukisan R. Bm Kpo | D21: 1500000 | E21: 450000 | F21: 0 | G21: =D21 -> 1500000 | H21: Belum Cair | I21: Penjualan Langsung/Lelang | O21: 450000 | W21: =SUM(J21:V21) -> 450000
A22: 21 | C22: Lukisan R. Hrd | D22: 3500000 | E22: 900000 | F22: 0 | G22: =D22 -> 3500000 | H22: Belum Cair | I22: Penjualan Langsung/Lelang | O22: 900000 | W22: =SUM(J22:V22) -> 900000
A23: 22 | C23: Lukisan Kupu2 | D23: 55000000 | E23: 4950000 | F23: 0 | G23: =D23 -> 55000000 | H23: Belum Cair | I23: Penjualan Langsung/Lelang | O23: 4950000 | W23: =SUM(J23:V23) -> 4950000
A24: 23 | C24: Lukisan 3 Wanita | D24: 12000000 | E24: 2250000 | F24: 0 | G24: =D24 -> 12000000 | H24: Belum Cair | I24: Penjualan Langsung/Lelang | O24: 2250000 | W24: =SUM(J24:V24) -> 2250000
A25: 24 | C25: Lukisan Wanita Penari | D25: 25000000 | E25: 1350000 | F25: 0 | G25: =D25 -> 25000000 | H25: Belum Cair | I25: Penjualan Langsung/Lelang | O25: 1350000 | W25: =SUM(J25:V25) -> 1350000
A26: 25 | C26: Lukisan Wanita Sawah | D26: 28000000 | E26: 900000 | F26: 0 | G26: =D26 -> 28000000 | H26: Belum Cair | I26: Penjualan Langsung/Lelang | O26: 900000 | W26: =SUM(J26:V26) -> 900000
... A49: 48 | C49: Gajah Berantai | D49: 3000000 | E49: 464000 | F49: 0 | G49: =D49 -> 3000000 | H49: Belum Cair | I49: Penjualan Langsung/Lelang | O49: 464000 | W49: =SUM(J49:V49) -> 464000
A50: 49 | C50: Patung Kuda Loncat | D50: 3000000 | E50: 464000 | F50: 470000 | H50: Cair
A51: 50 | C51: Patung Kuda | D51: 2500000 | E51: 388000 | F51: 0 | G51: =D51 -> 2500000 | H51: Belum Cair | I51: Penjualan Langsung/Lelang | O51: 388000 | W51: =SUM(J51:V51) -> 388000
A52: 51 | C52: Lampu Zebra | D52: 5000000 | E52: 772000 | F52: 0 | G52: =D52 -> 5000000 | H52: Belum Cair | I52: Penjualan Langsung/Lelang | O52: 772000 | W52: =SUM(J52:V52) -> 772000
A53: 52 | C53: Lampu Tingkat | D53: 3000000 | E53: 464000 | F53: 475000 | H53: Cair
A54: 53 | C54: Pembelian Kamera Nikon | D54: 25000000 | E54: 3860000 | F54: 0 | G54: =D54 -> 25000000 | H54: Belum Cair | I54: Penjualan Langsung/Lelang | O54: 3860000 | W54: =SUM(J54:V54) -> 3860000
A55: 54 | C55: Pembelian Kaca Hias | D55: 8000000 | E55: 1236000 | F55: 0 | G55: =D55 -> 8000000 | H55: Belum Cair | I55: Penjualan Langsung/Lelang | O55: 1236000 | W55: =SUM(J55:V55) -> 1236000
A56: 55 | C56: GENSET GATSU | D56: 100000000 | E56: 15448000 | F56: 16000000 | H56: Cair
A57: 56 | C57: Lukisan Model Perempuan Besar | D57: 35000000 | E57: 3600000 | F57: 0 | G57: =D57 -> 35000000 | H57: Belum Cair | I57: Penjualan Langsung/Lelang | O57: 3600000 | W57: =SUM(J57:V57) -> 3600000
A58: 57 | C58: 2 Buah Sofa Kerobokan A | D58: 10000000 | E58: 1544000 | F58: 0 | G58: =D58 -> 10000000 | H58: Belum Cair | I58: Penjualan Langsung/Lelang | O58: 1544000 | W58: =SUM(J58:V58) -> 1544000
A59: 58 | C59: 3 Buah Sofa Kerobokan B | D59: 9000000 | E59: 1392000 | F59: 0 | G59: =D59 -> 9000000 | H59: Belum Cair | I59: Penjualan Langsung/Lelang | O59: 1392000 | W59: =SUM(J59:V59) -> 1392000
A60: 59 | C60: 3 Buah Sofa Kerobokan C | D60: 9000000 | E60: 1392000 | F60: 0 | G60: =D60 -> 9000000 | H60: Belum Cair | I60: Penjualan Langsung/Lelang | O60: 1392000 | W60: =SUM(J60:V60) -> 1392000
A61: 60 | C61: 2 Buah Sofa Kerobokan D | D61: 12000000 | E61: 1852000 | F61: 0 | G61: =D61 -> 12000000 | H61: Belum Cair | I61: Penjualan Langsung/Lelang | O61: 1852000 | W61: =SUM(J61:V61) -> 1852000
A62: 61 | C62: 2 Buah Sofa Kerobokan E | D62: 10000000 | E62: 1544000 | F62: 0 | G62: =D62 -> 10000000 | H62: Belum Cair | I62: Penjualan Langsung/Lelang | O62: 1544000 | W62: =SUM(J62:V62) -> 1544000
A63: 62 | C63: 1 Buah Sofa Kerobokan F | D63: 7000000 | E63: 1080000 | F63: 0 | G63: =D63 -> 7000000 | H63: Belum Cair | I63: Penjualan Langsung/Lelang | O63: 1080000 | W63: =SUM(J63:V63) -> 1080000
A64: 63 | C64: 1 buah Sofa Kerobokan G | D64: 3500000 | E64: 540000 | F64: 0 | G64: =D64 -> 3500000 | H64: Belum Cair | I64: Penjualan Langsung/Lelang | O64: 540000 | W64: =SUM(J64:V64) -> 540000
A65: 64 | C65: 1 Buah Sofa Kerobokan H | D65: 1500000 | E65: 232000 | F65: 0 | G65: =D65 -> 1500000 | H65: Belum Cair | I65: Penjualan Langsung/Lelang | O65: 232000 | W65: =SUM(J65:V65) -> 232000
A66: 65 | C66: 1 Buah Sofa Kerobokan I | D66: 7500000 | E66: 1160000 | F66: 0 | G66: =D66 -> 7500000 | H66: Belum Cair | I66: Penjualan Langsung/Lelang | O66: 1160000 | W66: =SUM(J66:V66) -> 1160000
A67: 66 | C67: 1 Buah Lukisan 3 Anak Anak | D67: 50000000 | E67: 1125000 | F67: 0 | G67: =D67 -> 50000000 | H67: Belum Cair | I67: Penjualan Langsung/Lelang | O67: 1125000 | W67: =SUM(J67:V67) -> 1125000
A68: 67 | C68: 1 lukisan Bunga Kecil Kecil | D68: 40000000 | E68: 1350000 | F68: 0 | G68: =D68 -> 40000000 | H68: Belum Cair | I68: Penjualan Langsung/Lelang | O68: 1350000 | W68: =SUM(J68:V68) -> 1350000
... A73: 72 | C73: 1 Lukisan Pohon Di Hutan | D73: 12500000 | E73: 900000 | F73: 0 | G73: =D73 -> 12500000 | H73: Belum Cair | I73: Penjualan Langsung/Lelang | O73: 900000 | W73: =SUM(J73:V73) -> 900000
A74: 73 | C74: 2 Buah Sofa Belang | D74: 10000000 | E74: 1544000 | F74: 1550000 | H74: Cair
A75: 74 | C75: 2 Buah Lampu Meja | D75: 9000000 | E75: 928000 | F75: 0 | G75: =D75 -> 9000000 | H75: Belum Cair | I75: Penjualan Langsung/Lelang | O75: 928000 | W75: =SUM(J75:V75) -> 928000
A76: 75 | C76: 2 Buah Lampu Chanderlier | D76: 12000000 | E76: 1852000 | F76: 0 | G76: =D76 -> 12000000 | H76: Belum Cair | I76: Penjualan Langsung/Lelang | O76: 1852000 | W76: =SUM(J76:V76) -> 1852000
A77: 76 | C77: 1 Buah Kursi Kulit Sapi | D77: 7500000 | E77: 1160000 | F77: 1175000 | H77: Cair
A78: 77 | C78: 1 Buah Meja Bundar Kayu | D78: 2500000 | E78: 388000 | F78: 0 | G78: =D78 -> 2500000 | H78: Belum Cair | I78: Penjualan Langsung/Lelang | O78: 388000 | W78: =SUM(J78:V78) -> 388000
A79: 78 | C79: 1 Lukisan Pasar | D79: 5000000 | E79: 450000 | F79: 0 | G79: =D79 -> 5000000 | H79: Belum Cair | I79: Penjualan Langsung/Lelang | O79: 450000 | W79: =SUM(J79:V79) -> 450000
A80: 79 | C80: 1 Lukisan Kain Songket | D80: 18000000 | E80: 2250000 | F80: 0 | G80: =D80 -> 18000000 | H80: Belum Cair | I80: Penjualan Langsung/Lelang | O80: 2250000 | W80: =SUM(J80:V80) -> 2250000
A81: 80 | C81: Meja A | D81: 8500000 | E81: 1312000 | F81: 0 | G81: =D81 -> 8500000 | H81: Belum Cair | I81: Penjualan Langsung/Lelang | O81: 1312000 | W81: =SUM(J81:V81) -> 1312000
A82: 81 | C82: Meja B | D82: 4000000 | E82: 616000 | F82: 0 | G82: =D82 -> 4000000 | H82: Belum Cair | I82: Penjualan Langsung/Lelang | O82: 616000 | W82: =SUM(J82:V82) -> 616000
A83: 82 | C83: Bangku Panjang tanpa lengan | D83: 5000000 | E83: 772000 | F83: 785000 | H83: Cair
A84: 83 | C84: Bangku Panjang berlengan | D84: 5000000 | E84: 772000 | F84: 0 | G84: =D84 -> 5000000 | H84: Belum Cair | I84: Penjualan Langsung/Lelang | O84: 772000 | W84: =SUM(J84:V84) -> 772000
A85: 84 | C85: Meja C | D85: 3500000 | E85: 540000 | F85: 0 | G85: =D85 -> 3500000 | H85: Belum Cair | I85: Penjualan Langsung/Lelang | O85: 540000 | W85: =SUM(J85:V85) -> 540000
A86: 85 | C86: Meja D | D86: 6500000 | E86: 1004000 | F86: 0 | G86: =D86 -> 6500000 | H86: Belum Cair | I86: Penjualan Langsung/Lelang | O86: 1004000 | W86: =SUM(J86:V86) -> 1004000
A87: 86 | C87: 2 Meja E | D87: 7000000 | E87: 1080000 | F87: 0 | G87: =D87 -> 7000000 | H87: Belum Cair | I87: Penjualan Langsung/Lelang | O87: 1080000 | W87: =SUM(J87:V87) -> 1080000
A88: 87 | C88: 2 Meja F | D88: 7000000 | E88: 1080000 | F88: 0 | G88: =D88 -> 7000000 | H88: Belum Cair | I88: Penjualan Langsung/Lelang | O88: 1080000 | W88: =SUM(J88:V88) -> 1080000
A89: 88 | C89: 1 Lampu Gantung | D89: 15000000 | E89: 1852000 | F89: 0 | G89: =D89 -> 15000000 | H89: Belum Cair | I89: Penjualan Langsung/Lelang | O89: 1852000 | W89: =SUM(J89:V89) -> 1852000
A90: 89 | C90: 1 Lampu Gantung Warna Warni | D90: 15000000 | E90: 1852000 | F90: 0 | G90: =D90 -> 15000000 | H90: Belum Cair | I90: Penjualan Langsung/Lelang | O90: 1852000 | W90: =SUM(J90:V90) -> 1852000
A91: 90 | C91: Meja G | D91: 5000000 | E91: 772000 | F91: 0 | G91: =D91 -> 5000000 | H91: Belum Cair | I91: Penjualan Langsung/Lelang | O91: 772000 | W91: =SUM(J91:V91) -> 772000
A92: 91 | C92: Meja H | D92: 3500000 | E92: 540000 | F92: 0 | G92: =D92 -> 3500000 | H92: Belum Cair | I92: Penjualan Langsung/Lelang | O92: 540000 | W92: =SUM(J92:V92) -> 540000
A93: 92 | C93: Meja I | D93: 3500000 | E93: 540000 | F93: 0 | G93: =D93 -> 3500000 | H93: Belum Cair | I93: Penjualan Langsung/Lelang | O93: 540000 | W93: =SUM(J93:V93) -> 540000
A94: 93 | C94: Meja J | D94: 2000000 | E94: 308000 | F94: 350000 | H94: Cair
A95: 94 | C95: Kaca Hias Bundar | D95: 5000000 | E95: 772000 | F95: 0 | G95: =D95 -> 5000000 | H95: Belum Cair | I95: Penjualan Langsung/Lelang | O95: 772000 | W95: =SUM(J95:V95) -> 772000
A96: 95 | C96: Kaca Hias Kotak | D96: 4500000 | E96: 696000 | F96: 0 | G96: =D96 -> 4500000 | H96: Belum Cair | I96: Penjualan Langsung/Lelang | O96: 696000 | W96: =SUM(J96:V96) -> 696000
A97: 96 | C97: Kaca Hias Gelombang | D97: 4500000 | E97: 696000 | F97: 0 | G97: =D97 -> 4500000 | H97: Belum Cair | I97: Penjualan Langsung/Lelang | O97: 696000 | W97: =SUM(J97:V97) -> 696000
A98: 97 | C98: Meja K | D98: 3500000 | E98: 540000 | F98: 0 | G98: =D98 -> 3500000 | H98: Belum Cair | I98: Penjualan Langsung/Lelang | O98: 540000 | W98: =SUM(J98:V98) -> 540000
A99: 98 | C99: Meja L | D99: 6500000 | E99: 1004000 | F99: 0 | G99: =D99 -> 6500000 | H99: Belum Cair | I99: Penjualan Langsung/Lelang | O99: 1004000 | W99: =SUM(J99:V99) -> 1004000
A100: 99 | C100: Meja M | D100: 4000000 | E100: 616000 | F100: 0 | G100: =D100 -> 4000000 | H100: Belum Cair | I100: Penjualan Langsung/Lelang | O100: 616000 | W100: =SUM(J100:V100) -> 616000
A101: 100 | C101: Lemari A | D101: 35000000 | E101: 5408000 | F101: 0 | G101: =D101 -> 35000000 | H101: Belum Cair | I101: Penjualan Langsung/Lelang | O101: 5408000 | W101: =SUM(J101:V101) -> 5408000
A102: 101 | C102: Lemari B | D102: 10000000 | E102: 1544000 | F102: 0 | G102: =D102 -> 10000000 | H102: Belum Cair | I102: Penjualan Langsung/Lelang | O102: 1544000 | W102: =SUM(J102:V102) -> 1544000
A103: 102 | C103: Lemari C | D103: 15000000 | E103: 2316000 | F103: 0 | G103: =D103 -> 15000000 | H103: Belum Cair | I103: Penjualan Langsung/Lelang | O103: 2316000 | W103: =SUM(J103:V103) -> 2316000
A104: 103 | C104: Meja N | D104: 25000000 | E104: 3860000 | F104: 0 | G104: =D104 -> 25000000 | H104: Belum Cair | I104: Penjualan Langsung/Lelang | O104: 3860000 | W104: =SUM(J104:V104) -> 3860000
A105: 104 | C105: Meja O | D105: 25000000 | E105: 3860000 | F105: 0 | G105: =D105 -> 25000000 | H105: Belum Cair | I105: Penjualan Langsung/Lelang | O105: 3860000 | W105: =SUM(J105:V105) -> 3860000
A106: 105 | C106: Meja P | D106: 3500000 | E106: 540000 | F106: 0 | G106: =D106 -> 3500000 | H106: Belum Cair | I106: Penjualan Langsung/Lelang | O106: 540000 | W106: =SUM(J106:V106) -> 540000
... A108: 107 | C108: Meja R | D108: 10000000 | E108: 1544000 | F108: 0 | G108: =D108 -> 10000000 | H108: Belum Cair | I108: Penjualan Langsung/Lelang | O108: 1544000 | W108: =SUM(J108:V108) -> 1544000
A109: 108 | C109: 1 Kursi Panjang Kayu (Meja) | D109: 25000000 | E109: 3860000 | F109: 3875000 | H109: Cair
A110: 109 | C110: 2 Guci Kuning | D110: 10000000 | E110: 928000 | F110: 0 | G110: =D110 -> 10000000 | H110: Belum Cair | I110: Penjualan Langsung/Lelang | O110: 928000 | W110: =SUM(J110:V110) -> 928000
A111: 110 | C111: 2 Speaker | D111: 20000000 | E111: 3088000 | F111: 0 | G111: =D111 -> 20000000 | H111: Belum Cair | I111: Penjualan Langsung/Lelang | O111: 3088000 | W111: =SUM(J111:V111) -> 3088000
A112: 111 | C112: Patung Miniatur | D112: 4000000 | E112: 616000 | F112: 0 | G112: =D112 -> 4000000 | H112: Belum Cair | I112: Penjualan Langsung/Lelang | O112: 616000 | W112: =SUM(J112:V112) -> 616000
A113: 112 | C113: Karpet | D113: 55000000 | E113: 464000 | F113: 475000 | H113: Cair
A114: 113 | C114: Vas Bunga Dimeja Teller | D114: 6000000 | E114: 308000 | F114: 315000 | H114: Cair
A115: 114 | C115: Vas Bunga Lt 2 | D115: 7500000 | E115: 308000 | F115: 350000 | H115: Cair
A116: 115 | C116: Lukisan dibelakang Teller | D116: 60000000 | E116: 3600000 | F116: 0 | G116: =D116 -> 60000000 | H116: Belum Cair | I116: Penjualan Langsung/Lelang | O116: 3600000 | W116: =SUM(J116:V116) -> 3600000
A117: 116 | C117: Lukisan Gadis Bali Dibelakang CS | D117: 130000000 | E117: 3150000 | F117: 0 | G117: =D117 -> 130000000 | H117: Belum Cair | I117: Penjualan Langsung/Lelang | O117: 3150000 | W117: =SUM(J117:V117) -> 3150000
A118: 117 | C118: Rangkaian Bunga Hias | D118: 26000000 | E118: 156000 | F118: 0 | G118: =D118 -> 26000000 | H118: Belum Cair | I118: Penjualan Langsung/Lelang | O118: 156000 | W118: =SUM(J118:V118) -> 156000
A119: 118 | C119: 2 Bingkai Foto A,B | D119: 2000000 | E119: 308000 | F119: 0 | G119: =D119 -> 2000000 | H119: Belum Cair | I119: Penjualan Langsung/Lelang | O119: 308000 | W119: =SUM(J119:V119) -> 308000
A120: 119 | C120: 2 Bingkai Foto C,D | D120: 1000000 | E120: 156000 | F120: 0 | G120: =D120 -> 1000000 | H120: Belum Cair | I120: Penjualan Langsung/Lelang | O120: 156000 | W120: =SUM(J120:V120) -> 156000
A121: 120 | C121: 1 Karpet Kulit Sapi | D121: 4500000 | E121: 696000 | F121: 725000 | H121: Cair
A122: 121 | C122: 1 Taplak Meja Panjang di meja meeting | D122: 2000000 | E122: 36000 | F122: 45000 | H122: Cair
A123: 122 | C123: 1 Bunga Pintu Masuk tangga LT 1 | D123: 4000000 | E123: 616000 | F123: 0 | G123: =D123 -> 4000000 | H123: Belum Cair | I123: Penjualan Langsung/Lelang | O123: 616000 | W123: =SUM(J123:V123) -> 616000
A124: 123 | C124: 1 Bunga Pojok ruang BM | D124: 3500000 | E124: 540000 | F124: 550000 | H124: Cair
A125: 124 | C125: 1 Bunga di meja BM | D125: 1000000 | E125: 156000 | F125: 0 | G125: =D125 -> 1000000 | H125: Belum Cair | I125: Penjualan Langsung/Lelang | O125: 156000 | W125: =SUM(J125:V125) -> 156000
A126: 125 | C126: 1 Bunga CS | D126: 1000000 | E126: 156000 | F126: 0 | G126: =D126 -> 1000000 | H126: Belum Cair | I126: Penjualan Langsung/Lelang | O126: 156000 | W126: =SUM(J126:V126) -> 156000
A127: 126 | C127: 2 Bunga di ruang eksekutif | D127: 2000000 | E127: 308000 | F127: 350000 | H127: Cair
...

Sheet AYDA
A1: No. | B1: Nomor Rekening | C1: Nama Debitur | D1: Saldo (NP Audited) | E1: Saldo (LANAP) | F1: Nilai Likuidasi Agunan | G1: Realisasi Pencairan s.d. Mei 2021 | H1: Keterangan (Cair/Belum Dicairkan) | I1: Realisasi Upaya | J1: Strategi Pencairan | K1: 44348 | L1: 44378 | M1: 44409 | N1: 44440 | O1: 44470 | P1: 44501 | Q1: 44531 | R1: 44562 | S1: 44593 | T1: 44621 | U1: 44652 | V1: 44682 | W1: 44713 | X1: Total
A2: 1 | C2: I MADE IRWAN WIDIANA | D2: 2.4525567e+08 | E2: 2.7802208e+08 | F2: 0 | G2: 2.7802208e+08 | H2: Lunas | X2: =SUM(K2:W2) -> 0
A3: 2 | C3: I WAYAN JULI ADNYANA | D3: 3.7561415e+08 | E3: 3.7561415e+08 | F3: 751000000 | G3: 0 | H3: Belum Lunas | I3: Lelang I TAP | J3: Lelang 2 | P3: 159000000 | V3: 592000000 | X3: =SUM(K3:W3) -> 751000000
A4: 3 | C4: I MADE ASTRAGINA | D4: 8.029615e+08 | E4: 593000000 | F4: 593000000 | G4: 0 | H4: Belum Lunas | I4: Lelang I TAP | J4: Lelang 2 | Q4: 593000000 | X4: =SUM(K4:W4) -> 593000000
A5: 4 | C5: I GUSTI AGUNG PUTU DHARMA DHARWITA | D5: 3.0782287e+08 | E5: 132000000 | F5: 132000000 | G5: 0 | H5: Belum Lunas | I5: Lelang I TAP | J5: Lelang 2 | R5: 132000000 | X5: =SUM(K5:W5) -> 132000000
A6: 5 | C6: MONEY BHASKARA PUTRA | D6: 4.658356e+08 | E6: 233000000 | F6: 233000000 | G6: 0 | H6: Belum Lunas | I6: Lelang I TAP | J6: Lelang 2 | K6: 233000000 | X6: =SUM(K6:W6) -> 233000000
A7: 6 | C7: I GEDE DERESTI | D7: 1098038253 | E7: 779000000 | F7: 779000000 | G7: 0 | H7: Belum Lunas | I7: Lelang I TAP | J7: Lelang 2 | K7: 779000000 | X7: =SUM(K7:W7) -> 779000000
A8: 7 | C8: BAGUS KURNIAWAN | D8: 2.2881877e+09 | E8: 1070000000 | F8: 1070000000 | G8: 1309670503 | H8: Belum Lunas | I8: Lelang I LAKU | X8: =SUM(K8:W8) -> 0
A9: 8 | C9: GUSTI AYU MERTININGSIH | D9: 9.6826611e+08 | E9: 440000000 | F9: 440000000 | G9: 0 | H9: Belum Lunas | I9: Lelang I TAP | J9: Lelang 2 | S9: 440000000 | X9: =SUM(K9:W9) -> 440000000
A10: 9 | C10: I MADE YASA | D10: 335000000 | E10: 335000000 | F10: 624000000 | G10: 0 | H10: Belum Lunas | I10: Lelang I TAP | J10: Lelang 2 | T10: 4.6453333e+08 | X10: =SUM(K10:W10) -> 4.6453333e+08
A11: 10 | C11: I MADE YASA | D11: 115000000 | E11: 115000000 | F11: 0 | G11: 0 | H11: Belum Lunas | I11: Lelang I TAP | J11: Lelang 2 | T11: 1.5946667e+08 | X11: =SUM(K11:W11) -> 1.5946667e+08
A12: 11 | C12: I PUTU DANA | D12: 46506319 | E12: 46506319 | F12: 967000000 | G12: 0 | H12: Belum Lunas | I12: Lelang I TAP | J12: Lelang 2 | R12: 46053694 | X12: =SUM(K12:W12) -> 46053694
A13: 12 | C13: I PUTU DANA | D13: 1.6333087e+08 | E13: 163330868 | F13: 0 | G13: 0 | H13: Belum Lunas | I13: Lelang I TAP | J13: Lelang 2 | R13: 1.6174125e+08 | X13: =SUM(K13:W13) -> 1.6174125e+08
A14: 13 | C14: I PUTU DANA | D14: 766666665 | E14: 766666665 | F14: 0 | G14: 0 | H14: Belum Lunas | I14: Lelang I TAP | J14: Lelang 2 | R14: 7.5920506e+08 | X14: =SUM(K14:W14) -> 7.5920506e+08
A15: 14 | C15: I WAYAN BUDIANA | D15: 2.4575003e+09 | E15: 2183000000 | F15: 2183000000 | G15: 0 | H15: Belum Lunas | I15: Lelang I TAP | J15: Lelang 2 / Penjualan Sukarela | S15: 1.8795323e+09 | X15: =SUM(K15:W15) -> 1.8795323e+09
A16: 15 | C16: I WAYAN BUDIANA | D16: 396785869 | E16: 0 | F16: 0 | G16: 0 | H16: Belum Lunas | I16: Lelang I TAP | J16: Lelang 2 / Penjualan Sukarela | S16: 3.0346767e+08 | X16: =SUM(K16:W16) -> 3.0346767e+08
A17: 16 | C17: KOMANG ASTIKA YASA | D17: 2.4909596e+09 | E17: 2012000000 | F17: 2012000000 | G17: 0 | H17: Belum Lunas | I17: Lelang I TAP | J17: Lelang 2 | P17: 1.7548605e+09 | X17: =SUM(K17:W17) -> 1.7548605e+09
A18: 17 | C18: KOMANG ASTIKA YASA | D18: 365000000 | E18: 0 | F18: 0 | G18: 0 | H18: Belum Lunas | I18: Lelang I TAP | J18: Lelang 2 | P18: 2.5713949e+08 | X18: =SUM(K18:W18) -> 2.5713949e+08
A19: 18 | C19: HENNY | D19: 9.6157205e+08 | E19: 600000000 | F19: 600000000 | G19: 0 | H19: Belum Lunas | I19: Non HT | J19: Cessie | W19: 1 | X19: =SUM(K19:W19) -> 1
A20: 19 | C20: JUNANTO TJANDRAWINATA | D20: 2.1601976e+09 | E20: 315920000 | F20: 0 | G20: 0 | H20: Belum Lunas | I20: Proses Balik Nama Sertifikat | J20: Penjualan Sukarela | U20: 2.1601976e+09 | X20: =SUM(K20:W20) -> 2.1601976e+09
A21: 20 | C21: DANIEL KURNIAWAN | D21: 1.4130907e+09 | E21: 1413090694 | F21: 1658000000 | G21: 0 | H21: Belum Lunas | I21: Non HT | J21: Cessie | W21: 1 | X21: =SUM(K21:W21) -> 1
A22: 21 | C22: PUTU AGUS HERLLY DIANTARA | D22: 7.4728787e+08 | E22: 440000000 | F22: 404000000 | G22: 470812100 | H22: Belum Lunas | I22: Lelang I LAKU | X22: =SUM(K22:W22) -> 0
A23: 22 | C23: PUTU AGUS HERLLY DIANTARA | D23: 99951047 | E23: 0 | F23: 0 | G23: 0 | H23: Belum Lunas | I23: Lelang I LAKU | X23: =SUM(K23:W23) -> 0
A24: 23 | C24: CHRISTIAN SUGIANTO | D24: 1.0279274e+09 | E24: 1027927367 | F24: 1058000000 | G24: 0 | H24: Belum Lunas | I24: Non HT | J24: Cessie | W24: 1 | X24: =SUM(K24:W24) -> 1
D25: =SUM(D2:D24) -> 2.0098758e+10 | E25: =SUM(E2:E24) -> 1.3319078e+10 | G25: =SUM(G2:G24) -> 2.0585047e+09 | K25: =SUM(K2:K24) -> 1012000000 | L25: =SUM(L2:L24) -> 0 | M25: =SUM(M2:M24) -> 0 | N25: =SUM(N2:N24) -> 0 | O25: =SUM(O2:O24) -> 0 | P25: =SUM(P2:P24) -> 2171000000 | Q25: =SUM(Q2:Q24) -> 593000000 | R25: =SUM(R2:R24) -> 1099000000 | ... X25: =SUM(X2:X24) -> 1.0874198e+10

Sheet Prognosa Biaya
A2: No | B2: Jenis Aset/ Biaya | C2: Realisasi Pencairan/Biaya per 31 Mei 2021 | D2: Prognosa June 2021 | E2: 44378 | F2: 44409 | G2: 44440 | H2: 44470 | I2: 44501 | J2: 44531 | K2: 44562 | L2: 44593 | M2: 44621 | N2: 44652 | O2: 44682 | P2: 44713 | Q2: Dana Cadangan Pengakhiran | R2: Grand Total
B4: 1. Biaya Pendukung Likuidasi
A5: 1 | B5: Honor Tim Likuidasi | C5: =818416260+61823656 -> 880239916 | D5: 51544670 | E5: 51544670 | F5: 51544670 | G5: 51544670 | H5: 63573170 | I5: 63573170 | J5: 63573170 | K5: 63573170 | L5: 63573170 | M5: 63573170 | N5: 63573170 | O5: 63573170 | P5: 63573170 | R5: =SUM(C5:Q5) -> 1.6585771e+09
A6: 2 | B6: Honor Tenaga Pendukung | C6: =652084996+16459132 -> 668544128 | D6: 22750780 | E6: 22750780 | F6: 22750780 | G6: 22750780 | H6: 22750780 | I6: 22750780 | J6: 22750780 | K6: 22750780 | L6: 22750780 | M6: 22750780 | N6: 22750780 | O6: 22750780 | P6: 22750780 | R6: =SUM(C6:Q6) -> 964304268
A7: 3 | B7: Pembayaran THR Tim Likuidasi dan Tenaga Pendukung | C7: 104600949 | D7: 0 | E7: 0 | F7: 0 | G7: 0 | H7: 0 | I7: 0 | J7: 0 | K7: 0 | L7: 0 | M7: 0 | N7: 79176200 | O7: 0 | P7: 0 | R7: =SUM(C7:Q7) -> 183777149
A8: 4 | B8: Biaya kantor dan operasional lainya | C8: 362185568 | D8: 20146113 | E8: 20146113 | F8: 20146113 | G8: 20146113 | H8: 20146113 | I8: 20146113 | J8: 20146113 | K8: 20146113 | L8: 20146113 | M8: 20146113 | N8: 20146113 | O8: 20146113 | P8: 20146113 | R8: =SUM(C8:Q8) -> 6.2408503e+08
A9: 5 | B9: Insentif pencairan aset dan penagihan piutang | C9: 0 | P9: 1159271544 | R9: =SUM(C9:Q9) -> 1159271544
B10: Subtotal Biaya Pendukung | C10: =SUM(C5:C9) -> 2015570561 | D10: =SUM(D5:D9) -> 94441562 | E10: =SUM(E5:E9) -> 94441562 | F10: =SUM(F5:F9) -> 94441562 | G10: =SUM(G5:G9) -> 94441562 | H10: =SUM(H5:H9) -> 1.0647006e+08 | I10: =SUM(I5:I9) -> 1.0647006e+08 | J10: =SUM(J5:J9) -> 1.0647006e+08 | ... R10: =SUM(R5:R9) -> 4.5900151e+09
B11: 2. Biaya Kegiatan Likuidasi
A12: 1 | B12: Menyampaikan Rencana Kerja dan Anggaran TL. | C12: 318000 | D12: 95000 | E12: 95000 | F12: 95000 | G12: 95000 | H12: 95000 | I12: 95000 | J12: 95000 | K12: 95000 | L12: 95000 | M12: 95000 | N12: 95000 | O12: 95000 | P12: 95000 | R12: =SUM(C12:Q12) -> 1553000
A13: 2 | B13: Menindaklanjuti aspek legal pembubaran badan hukum bank. | C13: 7507500 | R13: =SUM(C13:Q13) -> 7507500
A14: 3 | B14: Menyelesaikan kewajiban kepada pegawai. | C14: 1079629772 | P14: 241103000 | R14: =SUM(C14:Q14) -> 1320732772
A15: 4 | B15: Menyampaikan Neraca Penutupan yang telah diaudit KAP/Inst. Pemerintah Bid. Audit kpd LPS. | C15: 115052750 | R15: =SUM(C15:Q15) -> 115052750
A16: 5 | B16: Melakukan inventarisasi aset dan kewajiban. | C16: 59216000 | E16: 3600000 | R16: =SUM(C16:Q16) -> 62816000
A17: 6 | B17: Melakukan penyelesaian kewajiban pihak yg menyebabkan bank gagal. | C17: 105155000 | E17: 27000000 | R17: =SUM(C17:Q17) -> 132155000
A18: 7 | B18: Menyampaikan Laporan Perubahan Aset Neto periode 2021 untuk mendapat persetujuan LPS. | C18: 98122000 | L18: 47400000 | R18: =SUM(C18:Q18) -> 145522000
A19: 8 | B19: Melakukan pencairan aset/inventarisasi aset | C19: 236132444 | J19: 396128000 | R19: =SUM(C19:Q19) -> 632260444
A20: 9 | B20: Melakukan penagihan kredit. | C20: 974639438 | D20: 1.2508512e+08 | E20: 1.2508512e+08 | F20: 1.2508512e+08 | G20: 1.2508512e+08 | H20: 1.2508512e+08 | I20: 1.2508512e+08 | J20: 1.2508512e+08 | K20: 1.2508512e+08 | L20: 1.2508512e+08 | M20: 1.2508512e+08 | N20: 1.2508512e+08 | O20: 1.2508512e+08 | P20: 1.2508512e+08 | R20: =SUM(C20:Q20) -> 2.600746e+09
A21: 10 | B21: Melakukan pembayaran kewajiban sesuai ketentuan | C21: 0 | P21: 4150000 | R21: =SUM(C21:Q21) -> 4150000
A22: 11 | B22: Menyampaikan Neraca Akhir Likuidasi kepada LPS. | C22: 0 | P22: 250000 | R22: =SUM(C22:Q22) -> 250000
A23: 12 | B23: Menindaklanjuti pengakhiran proses likuidasi. | C23: 0 | Q23: 328465650 | R23: =SUM(C23:Q23) -> 328465650
B24: Subtotal Biaya Kegiatan | C24: =SUM(C12:C23) -> 2675772904 | D24: =SUM(D12:D23) -> 1.2518012e+08 | E24: =SUM(E12:E23) -> 1.5578012e+08 | F24: =SUM(F12:F23) -> 1.2518012e+08 | G24: =SUM(G12:G23) -> 1.2518012e+08 | H24: =SUM(H12:H23) -> 1.2518012e+08 | I24: =SUM(I12:I23) -> 1.2518012e+08 | J24: =SUM(J12:J23) -> 5.2130812e+08 | ... R24: =SUM(R12:R23) -> 5.3512111e+09
B25: Total Biaya | C25: =C10+C24 -> 4691343465 | D25: =D10+D24 -> 2.1962168e+08 | E25: =E10+E24 -> 2.5022168e+08 | F25: =F10+F24 -> 2.1962168e+08 | G25: =G10+G24 -> 2.1962168e+08 | H25: =H10+H24 -> 2.3165018e+08 | I25: =I10+I24 -> 2.3165018e+08 | J25: =J10+J24 -> 6.2777818e+08 | ... R25: =R10+R24 -> 9.9412262e+09

Sheet Prognosa Penerimaan vs Biaya
A1: A. Tidak Dilakukan Perpanjangan
A3: Keterangan | B3: Realisasi sd 31 Mei 2021 | C3: Prognosa Juni 2021 | D3: Total Penerimaan/Biaya
A5: (1) | B5: (2) | C5: (3) | D5: (4) = (2) + (3)
A6: Kas | B6: =Net!F5 -> 41285600 | C6: 0 | D6: =SUM(B6:C6) -> 41285600
A7: Antar Bank Aktiva (ABA) | B7: =ABA!G19 -> 7.100292e+08 | C7: 0 | D7: =SUM(B7:C7) -> 7.100292e+08
A8: Kredit | B8: =Kredit!O200 -> 3.6047969e+10 | C8: =Kredit!AE200 -> 1.2967727e+09 | D8: =SUM(B8:C8) -> 3.7344742e+10
A9: Aktiva Tetap dan Inventaris
A10: - Tanah dan Bangunan | B10: ='Tanah dan Bangunan'!F4 -> 1177270000 | C10: ='Tanah dan Bangunan'!K4 -> 0 | D10: =SUM(B10:C10) -> 1177270000
A11: - Kendaraan | B11: =Kendaraan!F16 -> 1318200000 | C11: =Kendaraan!K16 -> 0 | D11: =SUM(B11:C11) -> 1318200000
A12: - Inventaris | B12: =Inventaris!F970 -> 179000000 | C12: =Inventaris!J970 -> 0 | D12: =SUM(B12:C12) -> 179000000
A13: Rupa-Rupa Aktiva
A14: - AYDA | B14: =AYDA!G25 -> 2.0585047e+09 | C14: =AYDA!K25 -> 1012000000 | D14: =SUM(B14:C14) -> 3.0705047e+09
A15: - PYAD | B15: =Kredit!P200 -> 3.9680295e+09 | C15: 0 | D15: =SUM(B15:C15) -> 3.9680295e+09
A16: - Akural Denda Kredit | B16: =Kredit!Q200 -> 5.1152048e+08 | C16: 0 | D16: =SUM(B16:C16) -> 5.1152048e+08
A17: - Penerimaan Lainnya | B17: 1.4492681e+09 | C17: 0 | D17: =SUM(B17:C17) -> 1.4492681e+09
A18: Total Penerimaan | B18: =SUM(B6:B17) -> 4.7461077e+10 | C18: =SUM(C6:C13) -> 1.2967727e+09 | D18: =SUM(B18:C18) -> 4.8757849e+10
A19: Biaya Pendukung Likuidasi | B19: ='Prognosa Biaya'!C10 -> 2015570561 | C19: ='Prognosa Biaya'!D10 -> 94441562 | D19: =B19+C19 -> 2.1100121e+09
A20: Biaya Kegiatan Likuidasi | B20: ='Prognosa Biaya'!C24 -> 2675772904 | C20: ='Prognosa Biaya'!D24 -> 1.2518012e+08 | D20: =B20+C20 -> 2.800953e+09
A21: Biaya Cadangan Pengakhiran | B21: 0 | C21: ='Prognosa Biaya'!Q23 -> 328465650 | D21: =B21+C21 -> 328465650
A22: Total Biaya Likuidasi | B22: =SUM(B19:B21) -> 4691343465 | C22: =SUM(C19:C21) -> 5.4808733e+08 | D22: =SUM(D19:D21) -> 5.2394308e+09
A23: Surplus/Defisit Likuidasi | B23: =B18-B22 -> 4.2769733e+10 | C23: =C18-C22 -> 7.4868535e+08 | D23: =D18-D22 -> 4.3518419e+10
A25: B. Opsi Perpanjangan 3 Bulan
A27: Keterangan | B27: Realisasi sd 31 Mei 2021 | C27: Prognosa Juni 2021 | D27: 44378 | E27: 44409 | F27: 44440 | G27: Total Penerimaan/Biaya
N28: =#REF!-#REF! -> #REF!
A29: (1) | B29: (2) | C29: (3) | D29: (4) | E29: (5) | F29: (6) | G29: (7) = (2) + (3) + (4) + (5) + (6)
A30: Kas | B30: =Net!F5 -> 41285600 | C30: 0 | G30: =SUM(B30:F30) -> 41285600
A31: Antar Bank Aktiva (ABA) | B31: =ABA!G19 -> 7.100292e+08 | C31: 0 | G31: =SUM(B31:F31) -> 7.100292e+08
A32: Kredit | B32: =Kredit!O200 -> 3.6047969e+10 | C32: =Kredit!AE200 -> 1.2967727e+09 | D32: =Kredit!AF200 -> 1.8236216e+09 | E32: =Kredit!AG200 -> 1.4557352e+09 | F32: =Kredit!AH200 -> 1.2727727e+09 | G32: =SUM(B32:F32) -> 4.1896871e+10
A33: Aktiva Tetap dan Inventaris | G33: =SUM(B33:F33) -> 0
A34: - Tanah dan Bangunan | B34: ='Tanah dan Bangunan'!F4 -> 1177270000 | C34: ='Tanah dan Bangunan'!K4 -> 0 | D34: ='Tanah dan Bangunan'!L4 -> 0 | E34: ='Tanah dan Bangunan'!M4 -> 0 | F34: ='Tanah dan Bangunan'!N4 -> 0 | G34: =SUM(B34:F34) -> 1177270000
A35: - Kendaraan | B35: =Kendaraan!F16 -> 1318200000 | C35: =Kendaraan!K16 -> 0 | D35: =Kendaraan!L16 -> 0 | E35: =Kendaraan!M16 -> 0 | F35: =Kendaraan!N16 -> 0 | G35: =SUM(B35:F35) -> 1318200000
A36: - Inventaris | B36: =Inventaris!F970 -> 179000000 | C36: =Inventaris!J970 -> 0 | D36: =Inventaris!K970 -> 0 | E36: =Inventaris!L970 -> 0 | F36: =Inventaris!M970 -> 0 | G36: =SUM(B36:F36) -> 179000000
A37: Rupa-Rupa Aktiva | G37: =SUM(B37:F37) -> 0
A38: - AYDA | B38: =AYDA!G25 -> 2.0585047e+09 | C38: =AYDA!K25 -> 1012000000 | D38: =AYDA!L25 -> 0 | E38: =AYDA!M25 -> 0 | F38: =AYDA!N25 -> 0 | G38: =SUM(B38:F38) -> 3.0705047e+09
A39: - PYAD | B39: =Kredit!P200 -> 3.9680295e+09 | C39: 0 | G39: =SUM(B39:F39) -> 3.9680295e+09
A40: - Akural Denda Kredit | B40: =Kredit!Q200 -> 5.1152048e+08 | C40: 0 | G40: =SUM(B40:F40) -> 5.1152048e+08
A41: - Penerimaan Lainnya | B41: 1.4492681e+09 | C41: 0 | G41: =SUM(B41:F41) -> 1.4492681e+09
A42: Total Penerimaan | B42: =SUM(B30:B41) -> 4.7461077e+10 | C42: =SUM(C30:C41) -> 2.3087727e+09 | D42: =SUM(D30:D41) -> 1.8236216e+09 | E42: =SUM(E30:E41) -> 1.4557352e+09 | F42: =SUM(F30:F41) -> 1.2727727e+09 | G42: =SUM(G30:G41) -> 5.4321979e+10
A43: Biaya Pendukung Likuidasi | B43: ='Prognosa Biaya'!C10 -> 2015570561 | C43: ='Prognosa Biaya'!D10 -> 94441562 | D43: ='Prognosa Biaya'!E10 -> 94441562 | E43: ='Prognosa Biaya'!F10 -> 94441562 | F43: ='Prognosa Biaya'!G10 -> 94441562 | G43: =SUM(B43:F43) -> 2.3933368e+09
A44: Biaya Kegiatan Likuidasi | B44: ='Prognosa Biaya'!C24 -> 2675772904 | C44: ='Prognosa Biaya'!D24 -> 1.2518012e+08 | D44: ='Prognosa Biaya'!E24 -> 1.5578012e+08 | E44: ='Prognosa Biaya'!F24 -> 1.2518012e+08 | F44: ='Prognosa Biaya'!G24 -> 1.2518012e+08 | G44: =SUM(B44:F44) -> 3.2070934e+09
A45: Biaya Cadangan Pengakhiran | B45: 0 | C45: ='Prognosa Biaya'!Q48 -> 0 | F45: ='Prognosa Biaya'!Q23 -> 328465650 | G45: =SUM(B45:F45) -> 328465650
A46: Total Biaya Likuidasi | B46: =SUM(B43:B45) -> 4691343465 | C46: =SUM(C43:C45) -> 2.1962168e+08 | D46: =SUM(D43:D45) -> 2.5022168e+08 | E46: =SUM(E43:E45) -> 2.1962168e+08 | F46: =SUM(F43:F45) -> 5.4808733e+08 | G46: =SUM(B46:F46) -> 5.9288958e+09
A47: Surplus/Defisit Likuidasi | B47: =B42-B46 -> 4.2769733e+10 | C47: =C42-C46 -> 2.089151e+09 | D47: =D42-D46 -> 1.5733999e+09 | E47: =E42-E46 -> 1.2361136e+09 | F47: =F42-F46 -> 7.2468535e+08 | G47: =G42-G46 -> 4.8393083e+10
A49: C. Opsi Perpanjangan 6 Bulan
A51: Keterangan | B51: Realisasi sd 31 Mei 2021 | C51: Prognosa Realisasi s.d. Sep-21 | D51: 44470 | E51: 44501 | F51: 44531 | G51: Total Penerimaan/Biaya
A53: (1) | B53: (2) | C53: (3) | D53: (4) | E53: (5) | F53: (6) | G53: (7) = (3) + (4) + (5) + (6)
A54: Kas | B54: 41285600 | C54: =G30 -> 41285600 | D54: 0 | E54: 0 | F54: 0 | G54: =SUM(C54:F54) -> 41285600
A55: Antar Bank Aktiva (ABA) | B55: 7.100292e+08 | C55: =G31 -> 7.100292e+08 | D55: 0 | E55: 0 | F55: 0 | G55: =SUM(C55:F55) -> 7.100292e+08
A56: Kredit | B56: 3.6047969e+10 | C56: =G32 -> 4.1896871e+10 | D56: =Kredit!AI200 -> 3.4626378e+09 | E56: =Kredit!AJ200 -> 2.6929556e+09 | F56: =Kredit!AK200 -> 1.8279462e+09 | G56: =SUM(C56:F56) -> 4.9880411e+10
A57: Aktiva Tetap dan Inventaris | G57: =SUM(C57:F57) -> 0
A58: - Tanah dan Bangunan | B58: 1177270000 | C58: =G34 -> 1177270000 | D58: ='Tanah dan Bangunan'!O4 -> 0 | E58: ='Tanah dan Bangunan'!P4 -> 0 | F58: ='Tanah dan Bangunan'!Q4 -> 5763901874 | G58: =SUM(C58:F58) -> 6941171874
A59: - Kendaraan | B59: 1318200000 | C59: =G35 -> 1318200000 | D59: =Kendaraan!O16 -> 0 | E59: =Kendaraan!P16 -> 0 | F59: =Kendaraan!Q16 -> 0 | G59: =SUM(C59:F59) -> 1318200000
A60: - Inventaris | B60: 179000000 | C60: =G36 -> 179000000 | D60: =Inventaris!N970 -> 196004100 | E60: =Inventaris!O970 -> 310309000 | F60: =Inventaris!P970 -> 0 | G60: =SUM(C60:F60) -> 685313100
A61: Rupa-Rupa Aktiva | C61: =G37 -> 0 | G61: =SUM(C61:F61) -> 0
A62: - AYDA | B62: 2.0585047e+09 | C62: =G38 -> 3.0705047e+09 | D62: =AYDA!L50 -> 0 | E62: =AYDA!M50 -> 0 | F62: =AYDA!N50 -> 0 | G62: =SUM(C62:F62) -> 3.0705047e+09
A63: - PYAD | B63: 3.9680295e+09 | C63: =G39 -> 3.9680295e+09 | D63: 0 | E63: 0 | F63: 0 | G63: =SUM(C63:F63) -> 3.9680295e+09
A64: - Akural Denda Kredit | B64: 5.1152048e+08 | C64: =G40 -> 5.1152048e+08 | D64: 0 | E64: 0 | F64: 0 | G64: =SUM(C64:F64) -> 5.1152048e+08
A65: - Penerimaan Lainnya | B65: 1.4492681e+09 | C65: =G41 -> 1.4492681e+09 | D65: 0 | E65: 0 | F65: 0 | G65: =SUM(C65:F65) -> 1.4492681e+09
A66: Total Penerimaan | B66: =SUM(B54:B65) -> 4.7461077e+10 | C66: =SUM(C54:C65) -> 5.4321979e+10 | D66: =SUM(D54:D65) -> 3.6586419e+09 | E66: =SUM(E54:E65) -> 3.0032646e+09 | F66: =SUM(F54:F65) -> 7.591848e+09 | G66: =SUM(G54:G65) -> 6.8575733e+10
A67: Biaya Pendukung Likuidasi | B67: ='Prognosa Biaya'!C10 -> 2015570561 | C67: =G43 -> 2.3933368e+09 | D67: ='Prognosa Biaya'!H10 -> 1.0647006e+08 | E67: ='Prognosa Biaya'!I10 -> 1.0647006e+08 | F67: ='Prognosa Biaya'!J10 -> 1.0647006e+08 | G67: =SUM(C67:F67) -> 2.712747e+09
A68: Biaya Kegiatan Likuidasi | B68: ='Prognosa Biaya'!C24 -> 2675772904 | C68: =G44 -> 3.2070934e+09 | D68: ='Prognosa Biaya'!H24 -> 1.2518012e+08 | E68: ='Prognosa Biaya'!I24 -> 1.2518012e+08 | F68: ='Prognosa Biaya'!J24 -> 5.2130812e+08 | G68: =SUM(C68:F68) -> 3.9787617e+09
A69: Biaya Cadangan Pengakhiran | B69: 0 | C69: 0 | F69: ='Prognosa Biaya'!Q24 -> 328465650 | G69: =SUM(C69:F69) -> 328465650
A70: Total Biaya Likuidasi | B70: =SUM(B67:B69) -> 4691343465 | C70: =SUM(C67:C69) -> 5.6004302e+09 | D70: =SUM(D67:D69) -> 2.3165018e+08 | E70: =SUM(E67:E69) -> 2.3165018e+08 | F70: =SUM(F67:F69) -> 9.5624383e+08 | G70: =SUM(C70:F70) -> 7.0199744e+09
A71: Surplus/Defisit Likuidasi | B71: =B66-B70 -> 4.2769733e+10 | C71: =C66-C70 -> 4.8721549e+10 | D71: =D66-D70 -> 3.4269917e+09 | E71: =E66-E70 -> 2.7716144e+09 | F71: =F66-F70 -> 6.6356042e+09 | G71: =G66-G70 -> 6.1555759e+10
A73: C. Opsi Perpanjangan 9 Bulan
A75: Keterangan | B75: Realisasi sd 31 Mei 2021 | C75: Prognosa Realisasi s.d. Dec-21 | D75: 44562 | E75: 44593 | F75: 44621 | G75: Total Penerimaan/Biaya
A77: (1) | B77: (2) | C77: (3) | D77: (4) | E77: (5) | F77: (6) | G77: (7) = (3) + (4) + (5) + (6)
A78: Kas | B78: 41285600 | C78: =G54 -> 41285600 | D78: 0 | E78: 0 | F78: 0 | G78: =SUM(C78:F78) -> 41285600
A79: Antar Bank Aktiva (ABA) | B79: 7.100292e+08 | C79: =G55 -> 7.100292e+08 | D79: 0 | E79: 0 | F79: 0 | G79: =SUM(C79:F79) -> 7.100292e+08
A80: Kredit | B80: 3.6047969e+10 | C80: =G56 -> 4.9880411e+10 | D80: =Kredit!AL200 -> 2.0027727e+09 | E80: =Kredit!AM200 -> 2.5437727e+09 | F80: =Kredit!AN200 -> 1.7039668e+09 | G80: =SUM(C80:F80) -> 5.6130923e+10
A81: Aktiva Tetap dan Inventaris | G81: =SUM(C81:F81) -> 0
A82: - Tanah dan Bangunan | B82: 1177270000 | C82: =G58 -> 6941171874 | D82: ='Tanah dan Bangunan'!R4 -> 0 | E82: ='Tanah dan Bangunan'!S4 -> 0 | F82: ='Tanah dan Bangunan'!T4 -> 0 | G82: =SUM(C82:F82) -> 6941171874
A83: - Kendaraan | B83: 1318200000 | C83: =G59 -> 1318200000 | D83: =Kendaraan!R16 -> 0 | E83: =Kendaraan!S16 -> 0 | F83: =Kendaraan!T16 -> 94200000 | G83: =SUM(C83:F83) -> 1412400000
A84: - Inventaris | B84: 179000000 | C84: =G60 -> 685313100 | D84: =Inventaris!Q970 -> 0 | E84: =Inventaris!R970 -> 0 | F84: =Inventaris!S970 -> 0 | G84: =SUM(C84:F84) -> 685313100
A85: Rupa-Rupa Aktiva | C85: =G61 -> 0 | G85: =SUM(C85:F85) -> 0
A86: - AYDA | B86: 2.0585047e+09 | C86: =G62 -> 3.0705047e+09 | D86: =AYDA!R25 -> 1099000000 | E86: =AYDA!S25 -> 2623000000 | F86: =AYDA!T25 -> 624000000 | G86: =SUM(C86:F86) -> 7.4165047e+09
A87: - PYAD | B87: 3.9680295e+09 | C87: =G63 -> 3.9680295e+09 | D87: 0 | E87: 0 | F87: 0 | G87: =SUM(C87:F87) -> 3.9680295e+09
A88: - Akural Denda Kredit | B88: 5.1152048e+08 | C88: =G64 -> 5.1152048e+08 | D88: 0 | E88: 0 | F88: 0 | G88: =SUM(C88:F88) -> 5.1152048e+08
A89: - Penerimaan Lainnya | B89: 1.4492681e+09 | C89: =G65 -> 1.4492681e+09 | D89: 0 | E89: 0 | F89: 0 | G89: =SUM(C89:F89) -> 1.4492681e+09
A90: Total Penerimaan | B90: =SUM(B78:B89) -> 4.7461077e+10 | C90: =SUM(C78:C89) -> 6.8575733e+10 | D90: =SUM(D78:D89) -> 3.1017727e+09 | E90: =SUM(E78:E89) -> 5.1667727e+09 | F90: =SUM(F78:F89) -> 2.4221668e+09 | G90: =SUM(G78:G89) -> 7.9266446e+10
A91: Biaya Pendukung Likuidasi | B91: ='Prognosa Biaya'!C10 -> 2015570561 | C91: =G67 -> 2.712747e+09 | D91: ='Prognosa Biaya'!K10 -> 1.0647006e+08 | E91: ='Prognosa Biaya'!L10 -> 1.0647006e+08 | F91: ='Prognosa Biaya'!M10 -> 1.0647006e+08 | G91: =SUM(C91:F91) -> 3.0321572e+09
A92: Biaya Kegiatan Likuidasi | B92: ='Prognosa Biaya'!C24 -> 2675772904 | C92: =G68 -> 3.9787617e+09 | D92: ='Prognosa Biaya'!K24 -> 1.2518012e+08 | E92: ='Prognosa Biaya'!L24 -> 1.7258012e+08 | F92: ='Prognosa Biaya'!M24 -> 1.2518012e+08 | G92: =SUM(C92:F92) -> 4.4017021e+09
A93: Biaya Cadangan Pengakhiran | B93: 0 | C93: 0 | F93: ='Prognosa Biaya'!Q24 -> 328465650 | G93: =SUM(C93:F93) -> 328465650
A94: Total Biaya Likuidasi | B94: =SUM(B91:B93) -> 4691343465 | C94: =SUM(C91:C93) -> 6.6915087e+09 | D94: =SUM(D91:D93) -> 2.3165018e+08 | E94: =SUM(E91:E93) -> 2.7905018e+08 | F94: =SUM(F91:F93) -> 5.6011583e+08 | G94: =SUM(C94:F94) -> 7.7623249e+09
A95: Surplus/Defisit Likuidasi | B95: =B90-B94 -> 4.2769733e+10 | C95: =C90-C94 -> 6.1884225e+10 | D95: =D90-D94 -> 2.8701225e+09 | E95: =E90-E94 -> 4.8877225e+09 | F95: =F90-F94 -> 1.862051e+09 | G95: =G90-G94 -> 7.1504121e+10
A97: C. Opsi Perpanjangan 12 Bulan
A99: Keterangan | B99: Realisasi sd 31 Mei 2021 | C99: Prognosa Realisasi s.d. Dec-21 | D99: 44652 | E99: 44682 | F99: 44713 | G99: Total Penerimaan/Biaya
A101: (1) | B101: (2) | C101: (3) | D101: (4) | E101: (5) | F101: (6) | G101: (7) = (3) + (4) + (5) + (6)
A102: Kas | B102: 41285600 | C102: =G78 -> 41285600 | D102: 0 | E102: 0 | F102: 0 | G102: =SUM(C102:F102) -> 41285600
A103: Antar Bank Aktiva (ABA) | B103: 7.100292e+08 | C103: =G79 -> 7.100292e+08 | D103: 0 | E103: 0 | F103: 0 | G103: =SUM(C103:F103) -> 7.100292e+08
A104: Kredit | B104: 3.6047969e+10 | C104: =G80 -> 5.6130923e+10 | D104: =Kredit!AO200 -> 1.5031107e+09 | E104: =Kredit!AP200 -> 3.332923e+09 | F104: =Kredit!AQ200 -> 1.0524283e+10 | G104: =SUM(C104:F104) -> 7.1491239e+10
A105: Aktiva Tetap dan Inventaris | G105: =SUM(C105:F105) -> 0
A106: - Tanah dan Bangunan | B106: 1177270000 | C106: =G82 -> 6941171874 | D106: ='Tanah dan Bangunan'!U4 -> 0 | E106: ='Tanah dan Bangunan'!V4 -> 0 | F106: ='Tanah dan Bangunan'!W4 -> 0 | G106: =SUM(C106:F106) -> 6941171874
A107: - Kendaraan | B107: 1318200000 | C107: =G83 -> 1412400000 | D107: =Kendaraan!U16 -> 0 | E107: =Kendaraan!V16 -> 0 | F107: =Kendaraan!W16 -> 0 | G107: =SUM(C107:F107) -> 1412400000
A108: - Inventaris | B108: 179000000 | C108: =G84 -> 685313100 | D108: =Inventaris!T970 -> 0 | E108: =Inventaris!U970 -> 0 | F108: =Inventaris!V970 -> 0 | G108: =SUM(C108:F108) -> 685313100
A109: Rupa-Rupa Aktiva | C109: =G85 -> 0 | G109: =SUM(C109:F109) -> 0
A110: - AYDA | B110: 2.0585047e+09 | C110: =G86 -> 7.4165047e+09 | D110: =AYDA!U25 -> 2.1601976e+09 | E110: =AYDA!V25 -> 592000000 | F110: =AYDA!W25 -> 3 | G110: =SUM(C110:F110) -> 1.0168702e+10
A111: - PYAD | B111: 3.9680295e+09 | C111: =G87 -> 3.9680295e+09 | D111: 0 | E111: 0 | F111: 0 | G111: =SUM(C111:F111) -> 3.9680295e+09
A112: - Akural Denda Kredit | B112: 5.1152048e+08 | C112: =G88 -> 5.1152048e+08 | D112: 0 | E112: 0 | F112: 0 | G112: =SUM(C112:F112) -> 5.1152048e+08
A113: - Penerimaan Lainnya | B113: 1.4492681e+09 | C113: =G89 -> 1.4492681e+09 | D113: 0 | E113: 0 | F113: 0 | G113: =SUM(C113:F113) -> 1.4492681e+09
...
